Workbook

Sheet Assumptions
A1: Параметр | B1: Значение | C1: Ед. | D1: Источник | E1: Достоверность | F1: Комментарий
A2: fx_usd | B2: 361.36 | C2: AMD/USD | D2: armenia_prices_competitors.md, armenia_costs_regulation_macro.md: ЦБА 19.10.2026 (подтв. verification_report.md A.9) | E2: факт
A3: fx_rub | B3: 4.3731 | C3: AMD/RUB | D3: armenia_prices_competitors.md: ЦБА 19.10.2026 | E3: факт
A4: cpi | B4: 0.043 | C4: доля/год | D4: armenia_costs_regulation_macro.md: ИПЦ сен-2026 г/г 4,3% | E4: факт | F4: индексация цен и фикс. расходов с 13-го и 25-го мес.
A5: refi_rate | B5: 0.0675 | C5: доля/год | D5: armenia_costs_regulation_macro.md: ставка ЦБ РА, 09.2026 | E5: факт
A6: discount_rate | B6: 0.18 | C6: доля/год | D6: оценка: ставка ЦБ 6,75% + премия за риск малого бизнеса/неликвидность/валюта ≈ 11 п.п. | E6: оценка | F6: диапазон 15–20%; NPV также при 15% и 20%
A7: avg_wage_am | B7: 314196 | C7: AMD/мес | D7: armenia_costs_regulation_macro.md: Armstat авг-2026 (подтв. verification_report.md A.10) | E7: факт
A8: avg_wage_ru | B8: 103612 | C8: RUB/мес | D8: Росстат, январь 2026 (glavkniga.ru/situations/k518592; 1prime.ru 01.04.2026) | E8: факт (вторичный источник)
A9: pop_yerevan | B9: 1147600 | C9: чел | D9: armenia_costs_regulation_macro.md: Armstat 01.01.2026 | E9: факт
A10: price_mens_A | B10: 2500 | C10: AMD | D10: armenia_prices_competitors.md §4: медиана эконом 3 000, дно 1 000–1 500, True Cost 3 000; −17% к медиане эконом | E10: решение | F10: не повышаем для компенсации v2: потолок — медиана эконом 3 000; чувствительность ±20% в G
A11: price_mens_B | B11: 3000 | C11: AMD | D11: armenia_prices_competitors.md: центр 3 000–5 000; = True Cost (15 мин вместо 30) | E11: решение
A12: mix | B12: 40/20/12/8/5/8/4/3 | C12: % услуг | D12: chio_chio_model.md: ЦА мужчины/дети/пенсионеры; armenia_prices_competitors.md §3: прокси ЮMoney | E12: допущение | F12: муж/машинка/дет/жен.кор/жен.дл/борода/укладка/корни; вариант «эконом-микс» в A; пересмотр по CRM через 3 мес.
A13: minutes_avg | B13: 18.65 | C13: мин/услуга | D13: chio_chio_model.md: 15 мин, 4–5 стрижек/час; взвешено по миксу | E13: оценка
A14: addon_share | B14: 0.12 | C14: доля услуг | D14: борода и укладка — доп. услуги к визиту (визитов = услуг × (1 − доля)) | E14: допущение
A15: hours_per_day | B15: 11 | C15: ч | D15: chio_chio_model.md: Казань 09–21; armenia_prices_competitors.md: Ереван 10–20/22 → 10:00–21:00 | E15: решение
A16: days_per_month | B16: 30.416667 | C16: дн | D16: 7/7 без санитарных дней | E16: допущение
A17: chairs | B17: 3 | C17: шт | D17: chio_chio_model.md: 2–3 кресла | E17: решение | F17: вариант 2 кресла в C/D
A18: masters | B18: 4 | C18: чел | D18: 3 кресла × 7 дн × 11 ч = 231 кресло-ч/нед; 4 мастера по 5–6 смен — законно только для ИП-мастеров (ТК РА 40/48 ч) | E18: решение
A19: load_mature_base | B19: 0.4 | C19: доля ёмкости | D19: verification_report.md C.5/D.2: 45% = средняя зрелая точка Чио Чио с брендом и колл-центром → для нового бренда 40% | E19: оценка
A20: load_mature_pess | B20: 0.3 | C20: доля | D20: verification_report.md D.2; chio_chio_model.md: «треть франчайзи убыточны» | E20: оценка
A21: load_mature_opt | B21: 0.45 | C21: доля | D21: chio_chio_model.md: средняя зрелая точка Чио Чио | E21: оценка
A22: load_shape | B22: м1 28% → м6 70% → м12 86% → м24 95% → м36 100% | C22: кривая | D22: chio_chio_model.md: кейсы Екб, spark, партнёр-2021; verification_report.md C.5 — согласуется | E22: оценка
A23: early_stress | B23: 0.5 | C23: множитель м1–3 | D23: verification_report.md C.5: стресс «первые 3 месяца на 50% ниже кривой» — для расчёта оборотного резерва | E23: допущение
A24: area_sqm | B24: 30 | C24: м² | D24: решение (v2, verification_report.md D.15): 3 поста ≈10,5 м² + ожидание 6–7 + зона персонала/хранение 4 + санузел с раковиной 3 + мойка 2,5 + проходы ≈4 → 30 м² удовлетворяет санправилам (файл 3 §5.1); Чио Чио 20–25 м²; v1 — 40 м² | E24: решение | F24: вариант 40 м² в C/G
A25: rent_sqm_sleep | B25: 6500 | C25: AMD/м²/мес | D25: armenia_costs_regulation_macro.md §1.2; verification_report.md A.24: выборка спальных районов n=3 (5 556 / 5 808 / 9 583), медиана 5 808, единственный малый формат 9 583 | E25: оценка (n=3) | F25: диапазон 5 800–9 600; стресс 9 500 в C и G; закрыть обзвоном 30 объектов
A26: rent_sqm_center | B26: 8500 | C26: AMD/м²/мес | D26: armenia_costs_regulation_macro.md §1.2: Кентрон (пересчёт verification_report.md: 8 451–8 667 для 20–120 м²) | E26: оценка (цены предложения)
A27: rent_sqm_center_1line | B27: 13000 | C27: AMD/м²/мес | D27: armenia_costs_regulation_macro.md §1.2: первая линия/витрина | E27: оценка (цены предложения)
A28: deposit_months | B28: 2 | C28: мес | D28: armenia_costs_regulation_macro.md | E28: факт
A29: fitout_months | B29: 1.25 | C29: мес | D29: verification_report.md C.6: аренда за период ремонта 1–1,5 мес. (каникулы не норма) | E29: оценка
A30: rent_documented | B30: 0 | C30: да/нет | D30: verification_report.md C.2: арендодатель-физлицо не выписывает расчётный документ ст. 55 ч. 2 НК → вычета 6% нет | E30: допущение (база = нет) | F30: если арендодатель — юрлицо/ИП с документами → True (вариант в C)
A31: fot_share_market | B31: 0.5 | C31: доля выручки | D31: armenia_costs_regulation_macro.md §2.1: вакансии «50/50»; verification_report.md C.3: в практике это доля на руки при неформальной оплате | E31: оценка (3–4 вакансии) | F31: в модели 50% — брутто-выплата (gross сотруднику или сумма ИП); схемы a/b/c в C
A32: fot_guarantee | B32: 200000 | C32: AMD/мес брутто | D32: verification_report.md D.8: 150 000 gross → 111 500 на руки < рынка 150–220 тыс.; 200 000 gross/ИП → ≈170 тыс. на руки | E32: оценка
A33: masters_ip | B33: 1 | C33: да/нет | D33: verification_report.md C.3: базовая схема — мастер-ИП на налоге с оборота, договор оказания услуг; выплата документирована → вычет 6% | E33: решение | F33: риск переквалификации в трудовые отношения — см. C
A34: ip_master_doc_exp | B34: 0.05 | C34: доля дохода | D34: документированные расходы самого ИП-мастера (инструмент, транспорт) — мало | E34: допущение
A35: manager_cost | B35: 120000 | C35: AMD/мес | D35: 0,5 ставки управляющего-наставника (сотрудник; не документируемый расход) | E35: допущение
A36: cleaning_cost | B36: 40000 | C36: AMD/мес | D36: уборка (сотрудник/физлицо) | E36: допущение
A37: host_cost | B37: 150000 | C37: AMD/мес | D37: verification_report.md D.7: администратор/хост на первые 6 мес. — опция, база 0 (киоск + мастера) | E37: допущение
A38: consumables_per_client | B38: 95 | C38: AMD/клиент | D38: armenia_costs_regulation_macro.md: 20–40 тыс. на 3 кресла; chio_chio_model.md: ~6% в РФ с косметикой; без мытья ниже | E38: оценка | F38: документированы (чеки поставщиков)
A39: consumables_floor | B39: 30000 | C39: AMD/мес | D39: armenia_costs_regulation_macro.md | E39: оценка
A40: utilities | B40: 75000 | C40: AMD/мес | D40: armenia_costs_regulation_macro.md §7: 60–90 тыс. на 40 м² | E40: оценка | F40: документированы (ENA, Veolia)
A41: it_crm | B41: 17000 | C41: AMD/мес | D41: alteg.io цены не публикует (проверено 20.10.2026); $10–12/сотр. × 4 + связь; альтернатива Fresha | E41: оценка
A42: hdm_monthly | B42: 3000 | C42: AMD/мес | D42: armenia_costs_regulation_macro.md §5.2: e-HDM | E42: факт
A43: hdm_setup | B43: 30000 | C43: AMD | D43: armenia_costs_regulation_macro.md §5.2 | E43: факт
A44: card_share | B44: 0.5 | C44: доля выручки | D44: armenia_prices_competitors.md §3; verification_report.md D.5: спальные 40%, центр 60% | E44: допущение
A45: acq_rate | B45: 0.012 | C45: доля безнала | D45: armenia_costs_regulation_macro.md §5.3 | E45: оценка
A46: acq_terminal | B46: 4600 | C46: AMD/мес | D46: armenia_costs_regulation_macro.md §5.3: IDBank | E46: факт
A47: marketing_y1 | B47: 0.05 | C47: доля выручки | D47: verification_report.md D.6: новый бренд без колл-центра/приложения УК → 5% в год 1 | E47: оценка
A48: marketing_y1_floor | B48: 120000 | C48: AMD/мес | D48: verification_report.md | E48: оценка
A49: marketing_pct | B49: 0.03 | C49: доля выручки | D49: chio_chio_model.md: модель УК 10 тыс.₽ при 150–300 тыс. (3–7%) → 3% с года 2 | E49: оценка
A50: marketing_floor | B50: 60000 | C50: AMD/мес | E50: оценка
A51: accounting | B51: 35000 | C51: AMD/мес | D51: аутсорс бухгалтерии ИП на налоге с оборота | E51: оценка
A52: accounting_ip_extra | B52: 15000 | C52: AMD/мес | D52: ведение отчётности 4 ИП-мастеров (схема c) | E52: допущение
A53: other_pct | B53: 0.02 | C53: доля выручки | D53: ремонт инструмента, форс-мажор | E53: допущение
A54: other_floor | B54: 20000 | C54: AMD/мес | E54: допущение
A55: other_documented_share | B55: 0.5 | C55: доля | E55: допущение
A56: ip_fixed | B56: 20000 | C56: AMD/мес | D56: armenia_costs_regulation_macro.md §4.2: подоходный 5 000 + соц. 5 000 + гербовый 120 000/год (доход >12 млн) = 20 000; verification_report.md A.18 подтв. | E56: факт | F56: окончательность подоходного ИП 5 000 при налоге с оборота — подтвердить у бухгалтера (verification_report.md B.1); иначе +20% с прибыли
A57: ip_oms_year | B57: 129600 | C57: AMD/год | D57: armenia_costs_regulation_macro.md; verification_report.md C.4/14: ОМС ИП обязателен при доходе прошлого года >2,4 млн → с 13-го месяца | E57: факт
A58: tt_rate | B58: 0.1 | C58: доля | D58: armenia_costs_regulation_macro.md §4.2; verification_report.md A.13 подтв. (fincore, alphaaccounting) | E58: факт
A59: tt_deduct | B59: 0.06 | C59: доля документированных расходов | D59: armenia_costs_regulation_macro.md; закон ՀՕ-72-Ն: расходы, подтверждённые расчётными документами ст. 55 ч. 2 п. 1–5 НК (счёт-фактура, накладная, чек ККМ) | E59: факт
A60: tt_floor | B60: 0.045 | C60: доля | D60: armenia_costs_regulation_macro.md | E60: факт
A61: tt_threshold | B61: 115000000 | C61: AMD/год | D61: armenia_costs_regulation_macro.md; verification_report.md A.14: PwC/fincore/profin 115 млн vs armenian-lawyer 120 млн — берём 115 | E61: факт (расхождение источников)
A62: uk_tax_royalty | B62: 0.1 | C62: доля | D62: verification_report.md C.9: роялти/паушальные — доход без вычета документированных расходов | E62: факт (вторичные источники)
A63: tt_trade_rate | B63: 0.1 | C63: доля | D63: armenia_costs_regulation_macro.md §4.2: торговля 10% − 9,5% закупок, мин. 1% (поставки расходников УК) | E63: факт
A64: royalty_chio | B64: 0.04 | C64: доля выручки | D64: chio_chio_model.md: 4%, мин. 5 000 ₽, со 2-го мес. (verification_report.md A.3 подтв.) | E64: факт
A65: royalty_chio_min_rub | B65: 5000 | C65: RUB/мес | D65: chio_chio_model.md | E65: факт
A66: fee_chio_lite_rub | B66: 290000 | C66: RUB | D66: chio_chio_model.md (verification_report.md A.2 подтв.) | E66: факт
A67: fee_chio_std_rub | B67: 590000 | C67: RUB | D67: chio_chio_model.md (verification_report.md A.1 подтв.) | E67: факт
A68: depr_months | B68: 60 | C68: мес | D68: 5 лет | E68: допущение
... A83: selfservice_it | B83: 250000 | C83: AMD | D83: киоск самообслуживания + ПК + камеры | E83: оценка
A84: crm_setup | B84: 30000 | C84: AMD | E84: оценка
A85: training | B85: 250000 | C85: AMD | D85: verification_report.md C.6: стажировка 4 мастеров 2 недели до открытия (гарантия) — 15-минутная технология | E85: оценка
A86: registration | B86: 3000 | C86: AMD | D86: armenia_costs_regulation_macro.md §4.4 | E86: факт
A87: legal_setup | B87: 60000 | C87: AMD | E87: оценка
A88: medbooks | B88: 60000 | C88: AMD | D88: armenia_costs_regulation_macro.md §5.1: 4 × 15 тыс. | E88: оценка
A89: launch_marketing | B89: 400000 | C89: AMD | D89: chio_chio_model.md: бесплатные стрижки на открытии, флаеры | E89: оценка
A90: contingency | B90: 0.15 | C90: доля hard-CAPEX | D90: verification_report.md C.6: факт CAPEX у франчайзи в 1,5–2 раза выше витрины → 15% | E90: допущение
A91: men_15_64_share | B91: 0.31 | C91: доля населения | D91: допущение (возрастная структура вне файлов) | E91: допущение
A92: kids_share | B92: 0.2 | C92: доля населения | D92: допущение | E92: допущение
A93: haircut_freq_men | B93: 10 | C93: раз/год | D93: armenia_prices_competitors.md §3: прокси ЮMoney; 3–5 недель → 8–12 | E93: допущение
A94: haircut_freq_kids | B94: 6 | C94: раз/год | D94: допущение | E94: допущение
A95: catchment_radius_km | B95: 1.2 | C95: км | D95: chio_chio_model.md: «у дома» | E95: допущение
A96: pop_per_point_base | B96: 60000 | C96: жит./точка | D96: verification_report.md C.9: Казань откатилась с 41–42 (2022) до 26 адресов (2026) = 1 на ~50 тыс.; Ереван плотнее по конкуренции (1 салон/720 жит.) → 1/60 тыс., диапазон 50–70 тыс. | E96: оценка
A97: pop_per_point_lo | B97: 70000 | C97: жит./точка | D97: нижняя граница | E97: оценка
A98: pop_per_point_hi | B98: 50000 | C98: жит./точка | D98: верхняя граница (= Казань-2026) | E98: оценка
A99: regions_pop | B99: Гюмри ~112 тыс., Ванадзор ~78 тыс., Абовян ~44 тыс., Вагаршапат ~47 тыс. | C99: чел | D99: ВНЕ ФАЙЛОВ: перепись 2022 (ориентир); в файлах — число парикмахерских 2ГИС 119/3/61/95 | E99: допущение
A100: own_royalty_min | B100: 50000 | C100: AMD/мес | D100: ≈2,3× минимума Чио Чио (21 866 AMD); со 2-го месяца | E100: предложение
A101: own_mkt_fund | B101: 0.01 | C101: доля выручки | D101: фонд внутри бюджета маркетинга франчайзи (не сверху) | E101: предложение
A102: supply_margin | B102: 0.2 | C102: доля закупок | D102: маржа УК на расходниках | E102: оценка
A103: uk_payroll | B103: 800000 | C103: AMD/мес gross | D103: 2 чел.: директор сети/запуск 450 тыс., тренер-технолог 350 тыс. | E103: оценка
A104: uk_other | B104: 500000 | C104: AMD/мес | D104: офис 100, IT 100, маркетинг бренда/SMM 150, юр./бух. 100, прочее 50 тыс. | E104: оценка
A105: uk_setup | B105: 3000000 | C105: AMD | D105: бренд-бук, стандарты, бизнес-бук, обучение, IT (разово) | E105: оценка
A106: own_fee | B106: 1000000 | C106: AMD | D106: предложение (пакет «founders» для первых 5–7 договоров): NPV субфранчайзи за 60 мес. > 0 @18%; verification_report.md D.11 | E106: предложение
A107: own_royalty | B107: 0.03 | C107: доля выручки | D107: предложение: 3%, мин. 50 000 (Чио Чио 4%, Прядки 3%) | E107: предложение
A109: ПАРАМЕТРЫ БАЗОВОГО СЦЕНАРИЯ (жёлтые — вход)
A110: sc_chairs | B110: 3 | C110: кресел
A111: sc_masters | B111: 4 | C111: мастеров
A112: sc_check | B112: =Prices!C12 | C112: средний чек (=Prices!C12)
A113: sc_price_mult | B113: 1 | C113: множитель цены
A114: sc_load_mature | B114: 0.4 | C114: зрелая загрузка
A115: sc_rent_sqm | B115: 6500 | C115: AMD/м²
...

Sheet Prices
A1: Услуга | B1: Цена A (спальный) | C1: Цена B (центр) | D1: Доля в миксе | E1: Мин/услуга | F1: Вклад A | G1: Вклад B | H1: Чио Чио Казань 2026, ₽ | I1: В AMD по 4,3731 | J1: Доп. услуга
A2: Мужская стрижка (ножницы/модельная) | B2: 2500 | C2: 3000 | D2: 0.4 | E2: 20 | F2: =B2*D2 | G2: =C2*D2 | H2: 700 | I2: =H2*Assumptions!$B$3 | J2: 0
A3: Стрижка машинкой (одна длина) | B3: 2000 | C3: 2500 | D3: 0.2 | E3: 15 | F3: =B3*D3 | G3: =C3*D3 | H3: 500 | I3: =H3*Assumptions!$B$3 | J3: 0
A4: Детская стрижка (до 12 лет) | B4: 2000 | C4: 2500 | D4: 0.12 | E4: 15 | F4: =B4*D4 | G4: =C4*D4 | H4: 500 | I4: =H4*Assumptions!$B$3 | J4: 0
A5: Женская стрижка короткая | B5: 2500 | C5: 3000 | D5: 0.08 | E5: 20 | F5: =B5*D5 | G5: =C5*D5 | H5: 800 | I5: =H5*Assumptions!$B$3 | J5: 0
A6: Женская стрижка длинная (без укладки) | B6: 3500 | C6: 4000 | D6: 0.05 | E6: 30 | F6: =B6*D6 | G6: =C6*D6 | H6: 800 | I6: =H6*Assumptions!$B$3 | J6: 0
A7: Борода / контур (доп. к визиту) | B7: 1500 | C7: 2000 | D7: 0.08 | E7: 10 | F7: =B7*D7 | G7: =C7*D7 | H7: 300 | I7: =H7*Assumptions!$B$3 | J7: 1
A8: Укладка феном без мытья (доп.) | B8: 1500 | C8: 2000 | D8: 0.04 | E8: 15 | F8: =B8*D8 | G8: =C8*D8 | J8: 1
A9: Окрашивание корней (опция, 1 тон) | B9: 5000 | C9: 6000 | D9: 0.03 | E9: 45 | F9: =B9*D9 | G9: =C9*D9 | H9: 2000 | I9: =H9*Assumptions!$B$3 | J9: 0
A11: Сумма долей | D11: =SUM(D2:D9)
A12: СРЕДНИЙ ЧЕК за услугу, AMD | C12: =SUM(F2:F9) | G12: =SUM(G2:G9)
A13: Средний чек в USD | C13: =C12/Assumptions!$B$2 | G13: =G12/Assumptions!$B$2
A14: Средний чек в RUB | C14: =C12/Assumptions!$B$3 | G14: =G12/Assumptions!$B$3
A15: Средневзвеш. мин/услуга | C15: =SUMPRODUCT(D2:D9,E2:E9)
A16: Доля доп. услуг | C16: =SUMPRODUCT(D2:D9,J2:J9)
A17: Средний чек за ВИЗИТ, AMD | C17: =C12/(1-C16) | G17: =G12/(1-C16)

Sheet CAPEX
A1: Статья | B1: Своя сеть 40 м² (AMD) | C1: Чио Чио «Лайт» | D1: Чио Чио стандарт | E1: Своя сеть 25 м², 2 кресла | F1: Своя сеть 40 м², USD
A2: Ремонт/отделка | B2: =Assumptions!$B$116*Assumptions!$B$69 | C2: =Assumptions!$B$116*Assumptions!$B$69 | D2: =Assumptions!$B$116*Assumptions!$B$69 | E2: =25*Assumptions!$B$69 | F2: =B2/Assumptions!$B$2
A3: Кресла | B3: =Assumptions!$B$110*Assumptions!$B$70 | C3: =Assumptions!$B$110*Assumptions!$B$70 | D3: =Assumptions!$B$110*Assumptions!$B$70 | E3: =2*Assumptions!$B$70 | F3: =B3/Assumptions!$B$2
A4: Рабочие посты | B4: =Assumptions!$B$110*Assumptions!$B$71 | C4: =Assumptions!$B$110*Assumptions!$B$71 | D4: =Assumptions!$B$110*Assumptions!$B$71 | E4: =2*Assumptions!$B$71 | F4: =B4/Assumptions!$B$2
A5: Мойка | B5: =Assumptions!$B$72 | C5: =Assumptions!$B$72 | D5: =Assumptions!$B$72 | E5: =Assumptions!$B$72 | F5: =B5/Assumptions!$B$2
A6: Вакуумные аппараты × 2 | B6: =2*Assumptions!$B$73 | C6: =2*Assumptions!$B$73 | D6: =2*Assumptions!$B$73 | E6: =2*Assumptions!$B$73 | F6: =B6/Assumptions!$B$2
A7: Инструмент/техника | B7: =Assumptions!$B$110*Assumptions!$B$74 | C7: =Assumptions!$B$110*Assumptions!$B$74 | D7: =Assumptions!$B$110*Assumptions!$B$74 | E7: =2*Assumptions!$B$74 | F7: =B7/Assumptions!$B$2
A8: НДС 20% на ввоз оборудования [v2] | B8: =(Assumptions!$B$110*Assumptions!$B$70+Assumptions!$B$72+2*Assumptions!$B$73+Assumptions!$B$110*Assumptions!$B$74)*Assumptions!$B$75 | C8: =(Assumptions!$B$110*Assumptions!$B$70+Assumptions!$B$72+2*Assumptions!$B$73+Assumptions!$B$110*Assumptions!$B$74)*Assumptions!$B$75 | D8: =(Assumptions!$B$110*Assumptions!$B$70+Assumptions!$B$72+2*Assumptions!$B$73+Assumptions!$B$110*Assumptions!$B$74)*Assumptions!$B$75 | E8: =(2*Assumptions!$B$70+Assumptions!$B$72+2*Assumptions!$B$73+2*Assumptions!$B$74)*Assumptions!$B$75 | F8: =B8/Assumptions!$B$2
A9: Кондиционеры + вентиляция [v2] | B9: =Assumptions!$B$77 | C9: =Assumptions!$B$77 | D9: =Assumptions!$B$77 | E9: =Assumptions!$B$77 | F9: =B9/Assumptions!$B$2
A10: Водонагреватель [v2] | B10: =Assumptions!$B$78 | C10: =Assumptions!$B$78 | D10: =Assumptions!$B$78 | E10: =Assumptions!$B$78 | F10: =B10/Assumptions!$B$2
A11: Стерилизатор | B11: =Assumptions!$B$76 | C11: =Assumptions!$B$76 | D11: =Assumptions!$B$76 | E11: =Assumptions!$B$76 | F11: =B11/Assumptions!$B$2
A12: Мебель ожидания/стойка | B12: =Assumptions!$B$79 | C12: =Assumptions!$B$79 | D12: =Assumptions!$B$79 | E12: =Assumptions!$B$79 | F12: =B12/Assumptions!$B$2
A13: Вывеска | B13: =Assumptions!$B$80 | C13: =Assumptions!$B$80 | D13: =Assumptions!$B$80 | E13: =Assumptions!$B$80 | F13: =B13/Assumptions!$B$2
A14: Согласование вывески (оценка) [v2] | B14: =Assumptions!$B$81 | C14: =Assumptions!$B$81 | D14: =Assumptions!$B$81 | E14: =Assumptions!$B$81 | F14: =B14/Assumptions!$B$2
A15: Брендинг интерьера | B15: =Assumptions!$B$82 | C15: =Assumptions!$B$82 | D15: =Assumptions!$B$82 | E15: =Assumptions!$B$82 | F15: =B15/Assumptions!$B$2
A16: Киоск/ПК/камеры | B16: =Assumptions!$B$83 | C16: =Assumptions!$B$83 | D16: =Assumptions!$B$83 | E16: =Assumptions!$B$83 | F16: =B16/Assumptions!$B$2
A17: Касса e-HDM | B17: =Assumptions!$B$43 | C17: =Assumptions!$B$43 | D17: =Assumptions!$B$43 | E17: =Assumptions!$B$43 | F17: =B17/Assumptions!$B$2
A18: Итого hard-CAPEX | B18: =SUM(B2:B17) | C18: =SUM(C2:C17) | D18: =SUM(D2:D17) | E18: =SUM(E2:E17) | F18: =B18/Assumptions!$B$2
A19: Непредвиденное 15% [v2] | B19: =B18*Assumptions!$B$90 | C19: =C18*Assumptions!$B$90 | D19: =D18*Assumptions!$B$90 | E19: =E18*Assumptions!$B$90 | F19: =B19/Assumptions!$B$2
A20: CRM/сайт | B20: =Assumptions!$B$84 | C20: =Assumptions!$B$84 | D20: =Assumptions!$B$84 | E20: =Assumptions!$B$84 | F20: =B20/Assumptions!$B$2
A21: Стажировка мастеров [v2] | B21: =Assumptions!$B$85 | C21: =Assumptions!$B$85 | D21: =Assumptions!$B$85 | E21: =Assumptions!$B$85 | F21: =B21/Assumptions!$B$2
A22: Регистрация ИП | B22: =Assumptions!$B$86 | C22: =Assumptions!$B$86 | D22: =Assumptions!$B$86 | E22: =Assumptions!$B$86 | F22: =B22/Assumptions!$B$2
A23: Юр./налоговое оформление | B23: =Assumptions!$B$87 | C23: =Assumptions!$B$87 | D23: =Assumptions!$B$87 | E23: =Assumptions!$B$87 | F23: =B23/Assumptions!$B$2
A24: Медкнижки | B24: =Assumptions!$B$88 | C24: =Assumptions!$B$88 | D24: =Assumptions!$B$88 | E24: =Assumptions!$B$88*3/4 | F24: =B24/Assumptions!$B$2
A25: Аренда за период ремонта [v2] | B25: =Assumptions!$B$29*Assumptions!$B$115*Assumptions!$B$116 | C25: =Assumptions!$B$29*Assumptions!$B$115*Assumptions!$B$116 | D25: =Assumptions!$B$29*Assumptions!$B$115*Assumptions!$B$116 | E25: =Assumptions!$B$29*Assumptions!$B$115*25 | F25: =B25/Assumptions!$B$2
A26: Депозит аренды | B26: =Assumptions!$B$28*Assumptions!$B$115*Assumptions!$B$116 | C26: =Assumptions!$B$28*Assumptions!$B$115*Assumptions!$B$116 | D26: =Assumptions!$B$28*Assumptions!$B$115*Assumptions!$B$116 | E26: =Assumptions!$B$28*Assumptions!$B$115*25 | F26: =B26/Assumptions!$B$2
A27: Маркетинг открытия | B27: =Assumptions!$B$89 | C27: =Assumptions!$B$89 | D27: =Assumptions!$B$89 | E27: =Assumptions!$B$89 | F27: =B27/Assumptions!$B$2
A28: Паушальный взнос | B28: 0 | C28: =Assumptions!$B$66*Assumptions!$B$3 | D28: =Assumptions!$B$67*Assumptions!$B$3 | E28: 0 | F28: =B28/Assumptions!$B$2
A29: ИТОГО CAPEX | B29: =B18+SUM(B19:B28) | C29: =C18+SUM(C19:C28) | D29: =D18+SUM(D19:D28) | E29: =E18+SUM(E19:E28) | F29: =B29/Assumptions!$B$2
A30: Итого CAPEX, USD | B30: =B29/Assumptions!$B$2 | C30: =C29/Assumptions!$B$2 | D30: =D29/Assumptions!$B$2 | E30: =E29/Assumptions!$B$2
A31: Итого CAPEX, RUB | B31: =B29/Assumptions!$B$3 | C31: =C29/Assumptions!$B$3 | D31: =D29/Assumptions!$B$3 | E31: =E29/Assumptions!$B$3
A32: Амортизируемая база (hard + непредвиденное + CRM + паушальный) | B32: =B18+B19+B20 | C32: =C18+C19+C20+C28 | D32: =D18+D19+D20+D28 | E32: =E18+E19+E20
A33: Оборотный резерв на стресс ramp-up (значение из Python; не входит в CAPEX) | B33: 2880170 | C33: 2994904 | D33: 2994904 | E33: 3217019
A34: ПОТРЕБНОСТЬ В ФИНАНСИРОВАНИИ = CAPEX + резерв | B34: =B29+B33 | C34: =C29+C33 | D34: =D29+D33 | E34: =E29+E33

Sheet PnL_36m
A1: Мес. | B1: Индекс цен | C1: Загрузка | D1: Услуг/день | E1: Средний чек | F1: ВЫРУЧКА | G1: Выплаты мастерам | H1: Аренда | I1: Управл.+уборка | J1: Расходники | K1: Коммуналка | L1: IT/связь | M1: Касса | N1: Эквайринг | O1: Маркетинг | P1: Бухгалтерия | Q1: Прочее | R1: Роялти | S1: Документ. расходы | T1: Налог с оборота | U1: Фиксы ИП | V1: ИТОГО РАСХОДЫ | W1: EBITDA | X1: Амортизация | Y1: ЧИСТАЯ ПРИБЫЛЬ | Z1: CF | AA1: Накопл. CF | AB1: Дисконт-фактор | AC1: Накопл. DCF
A2: 0 | Z2: =-CAPEX!$B$29 | AA2: =Z2 | AB2: 1 | AC2: =Z2
A3: 1 | B3: =(1+Assumptions!$B$4)^INT((A3-1)/12) | C3: =MIN(0.95,0.28*Assumptions!$B$114) | D3: =C3*Assumptions!$B$125 | E3: =Assumptions!$B$112*Assumptions!$B$113*B3 | F3: =D3*E3*Assumptions!$B$16 | G3: =MAX(Assumptions!$B$117*F3,Assumptions!$B$111*Assumptions!$B$32*B3) | H3: =Assumptions!$B$115*Assumptions!$B$116*B3 | I3: =(Assumptions!$B$124+Assumptions!$B$36)*B3 | J3: =MAX(Assumptions!$B$123*B3*D3*Assumptions!$B$16,Assumptions!$B$39*B3) | K3: =Assumptions!$B$40*B3 | L3: =Assumptions!$B$41*B3 | M3: =Assumptions!$B$42 | N3: =F3*Assumptions!$B$44*Assumptions!$B$45+Assumptions!$B$46 | O3: =IF(A3<=12,MAX(Assumptions!$B$47*F3,Assumptions!$B$48*B3),MAX(Assumptions!$B$49*F3,Assumptions!$B$50*B3)) | P3: =(Assumptions!$B$51+IF(Assumptions!$B$118=1,Assumptions!$B$52,0))*B3 | Q3: =MAX(Assumptions!$B$53*F3,Assumptions!$B$54*B3) | R3: =IF(AND(Assumptions!$B$120>0,A3>=2),MAX(Assumptions!$B$120*F3,Assumptions!$B$121),0) | S3: =J3+K3+L3+M3+N3+O3+P3+R3+Q3*Assumptions!$B$55+IF(Assumptions!$B$118=1,G3,0)+IF(Assumptions!$B$119=1,H3,0) | T3: =MAX(Assumptions!$B$58*F3-Assumptions!$B$59*S3,Assumptions!$B$60*F3) | U3: =Assumptions!$B$56+IF(A3>=13,Assumptions!$B$57/12,0) | V3: =SUM(G3:R3)+T3+U3 | W3: =F3-V3 | X3: =(CAPEX!$B$32+Assumptions!$B$122)/Assumptions!$B$68 | Y3: =W3-X3 | Z3: =W3 | AA3: =AA2+Z3 | AB3: =1/(1+((1+Assumptions!$B$6)^(1/12)-1))^A3 | AC3: =AC2+Z3*AB3
A4: 2 | B4: =(1+Assumptions!$B$4)^INT((A4-1)/12) | C4: =MIN(0.95,0.37*Assumptions!$B$114) | D4: =C4*Assumptions!$B$125 | E4: =Assumptions!$B$112*Assumptions!$B$113*B4 | F4: =D4*E4*Assumptions!$B$16 | G4: =MAX(Assumptions!$B$117*F4,Assumptions!$B$111*Assumptions!$B$32*B4) | H4: =Assumptions!$B$115*Assumptions!$B$116*B4 | I4: =(Assumptions!$B$124+Assumptions!$B$36)*B4 | J4: =MAX(Assumptions!$B$123*B4*D4*Assumptions!$B$16,Assumptions!$B$39*B4) | K4: =Assumptions!$B$40*B4 | L4: =Assumptions!$B$41*B4 | M4: =Assumptions!$B$42 | N4: =F4*Assumptions!$B$44*Assumptions!$B$45+Assumptions!$B$46 | O4: =IF(A4<=12,MAX(Assumptions!$B$47*F4,Assumptions!$B$48*B4),MAX(Assumptions!$B$49*F4,Assumptions!$B$50*B4)) | P4: =(Assumptions!$B$51+IF(Assumptions!$B$118=1,Assumptions!$B$52,0))*B4 | Q4: =MAX(Assumptions!$B$53*F4,Assumptions!$B$54*B4) | R4: =IF(AND(Assumptions!$B$120>0,A4>=2),MAX(Assumptions!$B$120*F4,Assumptions!$B$121),0) | S4: =J4+K4+L4+M4+N4+O4+P4+R4+Q4*Assumptions!$B$55+IF(Assumptions!$B$118=1,G4,0)+IF(Assumptions!$B$119=1,H4,0) | T4: =MAX(Assumptions!$B$58*F4-Assumptions!$B$59*S4,Assumptions!$B$60*F4) | U4: =Assumptions!$B$56+IF(A4>=13,Assumptions!$B$57/12,0) | V4: =SUM(G4:R4)+T4+U4 | W4: =F4-V4 | X4: =(CAPEX!$B$32+Assumptions!$B$122)/Assumptions!$B$68 | Y4: =W4-X4 | Z4: =W4 | AA4: =AA3+Z4 | AB4: =1/(1+((1+Assumptions!$B$6)^(1/12)-1))^A4 | AC4: =AC3+Z4*AB4
A5: 3 | B5: =(1+Assumptions!$B$4)^INT((A5-1)/12) | C5: =MIN(0.95,0.47*Assumptions!$B$114) | D5: =C5*Assumptions!$B$125 | E5: =Assumptions!$B$112*Assumptions!$B$113*B5 | F5: =D5*E5*Assumptions!$B$16 | G5: =MAX(Assumptions!$B$117*F5,Assumptions!$B$111*Assumptions!$B$32*B5) | H5: =Assumptions!$B$115*Assumptions!$B$116*B5 | I5: =(Assumptions!$B$124+Assumptions!$B$36)*B5 | J5: =MAX(Assumptions!$B$123*B5*D5*Assumptions!$B$16,Assumptions!$B$39*B5) | K5: =Assumptions!$B$40*B5 | L5: =Assumptions!$B$41*B5 | M5: =Assumptions!$B$42 | N5: =F5*Assumptions!$B$44*Assumptions!$B$45+Assumptions!$B$46 | O5: =IF(A5<=12,MAX(Assumptions!$B$47*F5,Assumptions!$B$48*B5),MAX(Assumptions!$B$49*F5,Assumptions!$B$50*B5)) | P5: =(Assumptions!$B$51+IF(Assumptions!$B$118=1,Assumptions!$B$52,0))*B5 | Q5: =MAX(Assumptions!$B$53*F5,Assumptions!$B$54*B5) | R5: =IF(AND(Assumptions!$B$120>0,A5>=2),MAX(Assumptions!$B$120*F5,Assumptions!$B$121),0) | S5: =J5+K5+L5+M5+N5+O5+P5+R5+Q5*Assumptions!$B$55+IF(Assumptions!$B$118=1,G5,0)+IF(Assumptions!$B$119=1,H5,0) | T5: =MAX(Assumptions!$B$58*F5-Assumptions!$B$59*S5,Assumptions!$B$60*F5) | U5: =Assumptions!$B$56+IF(A5>=13,Assumptions!$B$57/12,0) | V5: =SUM(G5:R5)+T5+U5 | W5: =F5-V5 | X5: =(CAPEX!$B$32+Assumptions!$B$122)/Assumptions!$B$68 | Y5: =W5-X5 | Z5: =W5 | AA5: =AA4+Z5 | AB5: =1/(1+((1+Assumptions!$B$6)^(1/12)-1))^A5 | AC5: =AC4+Z5*AB5
A6: 4 | B6: =(1+Assumptions!$B$4)^INT((A6-1)/12) | C6: =MIN(0.95,0.56*Assumptions!$B$114) | D6: =C6*Assumptions!$B$125 | E6: =Assumptions!$B$112*Assumptions!$B$113*B6 | F6: =D6*E6*Assumptions!$B$16 | G6: =MAX(Assumptions!$B$117*F6,Assumptions!$B$111*Assumptions!$B$32*B6) | H6: =Assumptions!$B$115*Assumptions!$B$116*B6 | I6: =(Assumptions!$B$124+Assumptions!$B$36)*B6 | J6: =MAX(Assumptions!$B$123*B6*D6*Assumptions!$B$16,Assumptions!$B$39*B6) | K6: =Assumptions!$B$40*B6 | L6: =Assumptions!$B$41*B6 | M6: =Assumptions!$B$42 | N6: =F6*Assumptions!$B$44*Assumptions!$B$45+Assumptions!$B$46 | O6: =IF(A6<=12,MAX(Assumptions!$B$47*F6,Assumptions!$B$48*B6),MAX(Assumptions!$B$49*F6,Assumptions!$B$50*B6)) | P6: =(Assumptions!$B$51+IF(Assumptions!$B$118=1,Assumptions!$B$52,0))*B6 | Q6: =MAX(Assumptions!$B$53*F6,Assumptions!$B$54*B6) | R6: =IF(AND(Assumptions!$B$120>0,A6>=2),MAX(Assumptions!$B$120*F6,Assumptions!$B$121),0) | S6: =J6+K6+L6+M6+N6+O6+P6+R6+Q6*Assumptions!$B$55+IF(Assumptions!$B$118=1,G6,0)+IF(Assumptions!$B$119=1,H6,0) | T6: =MAX(Assumptions!$B$58*F6-Assumptions!$B$59*S6,Assumptions!$B$60*F6) | U6: =Assumptions!$B$56+IF(A6>=13,Assumptions!$B$57/12,0) | V6: =SUM(G6:R6)+T6+U6 | W6: =F6-V6 | X6: =(CAPEX!$B$32+Assumptions!$B$122)/Assumptions!$B$68 | Y6: =W6-X6 | Z6: =W6 | AA6: =AA5+Z6 | AB6: =1/(1+((1+Assumptions!$B$6)^(1/12)-1))^A6 | AC6: =AC5+Z6*AB6
A7: 5 | B7: =(1+Assumptions!$B$4)^INT((A7-1)/12) | C7: =MIN(0.95,0.63*Assumptions!$B$114) | D7: =C7*Assumptions!$B$125 | E7: =Assumptions!$B$112*Assumptions!$B$113*B7 | F7: =D7*E7*Assumptions!$B$16 | G7: =MAX(Assumptions!$B$117*F7,Assumptions!$B$111*Assumptions!$B$32*B7) | H7: =Assumptions!$B$115*Assumptions!$B$116*B7 | I7: =(Assumptions!$B$124+Assumptions!$B$36)*B7 | J7: =MAX(Assumptions!$B$123*B7*D7*Assumptions!$B$16,Assumptions!$B$39*B7) | K7: =Assumptions!$B$40*B7 | L7: =Assumptions!$B$41*B7 | M7: =Assumptions!$B$42 | N7: =F7*Assumptions!$B$44*Assumptions!$B$45+Assumptions!$B$46 | O7: =IF(A7<=12,MAX(Assumptions!$B$47*F7,Assumptions!$B$48*B7),MAX(Assumptions!$B$49*F7,Assumptions!$B$50*B7)) | P7: =(Assumptions!$B$51+IF(Assumptions!$B$118=1,Assumptions!$B$52,0))*B7 | Q7: =MAX(Assumptions!$B$53*F7,Assumptions!$B$54*B7) | R7: =IF(AND(Assumptions!$B$120>0,A7>=2),MAX(Assumptions!$B$120*F7,Assumptions!$B$121),0) | S7: =J7+K7+L7+M7+N7+O7+P7+R7+Q7*Assumptions!$B$55+IF(Assumptions!$B$118=1,G7,0)+IF(Assumptions!$B$119=1,H7,0) | T7: =MAX(Assumptions!$B$58*F7-Assumptions!$B$59*S7,Assumptions!$B$60*F7) | U7: =Assumptions!$B$56+IF(A7>=13,Assumptions!$B$57/12,0) | V7: =SUM(G7:R7)+T7+U7 | W7: =F7-V7 | X7: =(CAPEX!$B$32+Assumptions!$B$122)/Assumptions!$B$68 | Y7: =W7-X7 | Z7: =W7 | AA7: =AA6+Z7 | AB7: =1/(1+((1+Assumptions!$B$6)^(1/12)-1))^A7 | AC7: =AC6+Z7*AB7
A8: 6 | B8: =(1+Assumptions!$B$4)^INT((A8-1)/12) | C8: =MIN(0.95,0.7*Assumptions!$B$114) | D8: =C8*Assumptions!$B$125 | E8: =Assumptions!$B$112*Assumptions!$B$113*B8 | F8: =D8*E8*Assumptions!$B$16 | G8: =MAX(Assumptions!$B$117*F8,Assumptions!$B$111*Assumptions!$B$32*B8) | H8: =Assumptions!$B$115*Assumptions!$B$116*B8 | I8: =(Assumptions!$B$124+Assumptions!$B$36)*B8 | J8: =MAX(Assumptions!$B$123*B8*D8*Assumptions!$B$16,Assumptions!$B$39*B8) | K8: =Assumptions!$B$40*B8 | L8: =Assumptions!$B$41*B8 | M8: =Assumptions!$B$42 | N8: =F8*Assumptions!$B$44*Assumptions!$B$45+Assumptions!$B$46 | O8: =IF(A8<=12,MAX(Assumptions!$B$47*F8,Assumptions!$B$48*B8),MAX(Assumptions!$B$49*F8,Assumptions!$B$50*B8)) | P8: =(Assumptions!$B$51+IF(Assumptions!$B$118=1,Assumptions!$B$52,0))*B8 | Q8: =MAX(Assumptions!$B$53*F8,Assumptions!$B$54*B8) | R8: =IF(AND(Assumptions!$B$120>0,A8>=2),MAX(Assumptions!$B$120*F8,Assumptions!$B$121),0) | S8: =J8+K8+L8+M8+N8+O8+P8+R8+Q8*Assumptions!$B$55+IF(Assumptions!$B$118=1,G8,0)+IF(Assumptions!$B$119=1,H8,0) | T8: =MAX(Assumptions!$B$58*F8-Assumptions!$B$59*S8,Assumptions!$B$60*F8) | U8: =Assumptions!$B$56+IF(A8>=13,Assumptions!$B$57/12,0) | V8: =SUM(G8:R8)+T8+U8 | W8: =F8-V8 | X8: =(CAPEX!$B$32+Assumptions!$B$122)/Assumptions!$B$68 | Y8: =W8-X8 | Z8: =W8 | AA8: =AA7+Z8 | AB8: =1/(1+((1+Assumptions!$B$6)^(1/12)-1))^A8 | AC8: =AC7+Z8*AB8
A9: 7 | B9: =(1+Assumptions!$B$4)^INT((A9-1)/12) | C9: =MIN(0.95,0.74*Assumptions!$B$114) | D9: =C9*Assumptions!$B$125 | E9: =Assumptions!$B$112*Assumptions!$B$113*B9 | F9: =D9*E9*Assumptions!$B$16 | G9: =MAX(Assumptions!$B$117*F9,Assumptions!$B$111*Assumptions!$B$32*B9) | H9: =Assumptions!$B$115*Assumptions!$B$116*B9 | I9: =(Assumptions!$B$124+Assumptions!$B$36)*B9 | J9: =MAX(Assumptions!$B$123*B9*D9*Assumptions!$B$16,Assumptions!$B$39*B9) | K9: =Assumptions!$B$40*B9 | L9: =Assumptions!$B$41*B9 | M9: =Assumptions!$B$42 | N9: =F9*Assumptions!$B$44*Assumptions!$B$45+Assumptions!$B$46 | O9: =IF(A9<=12,MAX(Assumptions!$B$47*F9,Assumptions!$B$48*B9),MAX(Assumptions!$B$49*F9,Assumptions!$B$50*B9)) | P9: =(Assumptions!$B$51+IF(Assumptions!$B$118=1,Assumptions!$B$52,0))*B9 | Q9: =MAX(Assumptions!$B$53*F9,Assumptions!$B$54*B9) | R9: =IF(AND(Assumptions!$B$120>0,A9>=2),MAX(Assumptions!$B$120*F9,Assumptions!$B$121),0) | S9: =J9+K9+L9+M9+N9+O9+P9+R9+Q9*Assumptions!$B$55+IF(Assumptions!$B$118=1,G9,0)+IF(Assumptions!$B$119=1,H9,0) | T9: =MAX(Assumptions!$B$58*F9-Assumptions!$B$59*S9,Assumptions!$B$60*F9) | U9: =Assumptions!$B$56+IF(A9>=13,Assumptions!$B$57/12,0) | V9: =SUM(G9:R9)+T9+U9 | W9: =F9-V9 | X9: =(CAPEX!$B$32+Assumptions!$B$122)/Assumptions!$B$68 | Y9: =W9-X9 | Z9: =W9 | AA9: =AA8+Z9 | AB9: =1/(1+((1+Assumptions!$B$6)^(1/12)-1))^A9 | AC9: =AC8+Z9*AB9
A10: 8 | B10: =(1+Assumptions!$B$4)^INT((A10-1)/12) | C10: =MIN(0.95,0.77*Assumptions!$B$114) | D10: =C10*Assumptions!$B$125 | E10: =Assumptions!$B$112*Assumptions!$B$113*B10 | F10: =D10*E10*Assumptions!$B$16 | G10: =MAX(Assumptions!$B$117*F10,Assumptions!$B$111*Assumptions!$B$32*B10) | H10: =Assumptions!$B$115*Assumptions!$B$116*B10 | I10: =(Assumptions!$B$124+Assumptions!$B$36)*B10 | J10: =MAX(Assumptions!$B$123*B10*D10*Assumptions!$B$16,Assumptions!$B$39*B10) | K10: =Assumptions!$B$40*B10 | L10: =Assumptions!$B$41*B10 | M10: =Assumptions!$B$42 | N10: =F10*Assumptions!$B$44*Assumptions!$B$45+Assumptions!$B$46 | O10: =IF(A10<=12,MAX(Assumptions!$B$47*F10,Assumptions!$B$48*B10),MAX(Assumptions!$B$49*F10,Assumptions!$B$50*B10)) | P10: =(Assumptions!$B$51+IF(Assumptions!$B$118=1,Assumptions!$B$52,0))*B10 | Q10: =MAX(Assumptions!$B$53*F10,Assumptions!$B$54*B10) | R10: =IF(AND(Assumptions!$B$120>0,A10>=2),MAX(Assumptions!$B$120*F10,Assumptions!$B$121),0) | S10: =J10+K10+L10+M10+N10+O10+P10+R10+Q10*Assumptions!$B$55+IF(Assumptions!$B$118=1,G10,0)+IF(Assumptions!$B$119=1,H10,0) | T10: =MAX(Assumptions!$B$58*F10-Assumptions!$B$59*S10,Assumptions!$B$60*F10) | U10: =Assumptions!$B$56+IF(A10>=13,Assumptions!$B$57/12,0) | V10: =SUM(G10:R10)+T10+U10 | W10: =F10-V10 | X10: =(CAPEX!$B$32+Assumptions!$B$122)/Assumptions!$B$68 | Y10: =W10-X10 | Z10: =W10 | AA10: =AA9+Z10 | AB10: =1/(1+((1+Assumptions!$B$6)^(1/12)-1))^A10 | AC10: =AC9+Z10*AB10
A11: 9 | B11: =(1+Assumptions!$B$4)^INT((A11-1)/12) | C11: =MIN(0.95,0.79*Assumptions!$B$114) | D11: =C11*Assumptions!$B$125 | E11: =Assumptions!$B$112*Assumptions!$B$113*B11 | F11: =D11*E11*Assumptions!$B$16 | G11: =MAX(Assumptions!$B$117*F11,Assumptions!$B$111*Assumptions!$B$32*B11) | H11: =Assumptions!$B$115*Assumptions!$B$116*B11 | I11: =(Assumptions!$B$124+Assumptions!$B$36)*B11 | J11: =MAX(Assumptions!$B$123*B11*D11*Assumptions!$B$16,Assumptions!$B$39*B11) | K11: =Assumptions!$B$40*B11 | L11: =Assumptions!$B$41*B11 | M11: =Assumptions!$B$42 | N11: =F11*Assumptions!$B$44*Assumptions!$B$45+Assumptions!$B$46 | O11: =IF(A11<=12,MAX(Assumptions!$B$47*F11,Assumptions!$B$48*B11),MAX(Assumptions!$B$49*F11,Assumptions!$B$50*B11)) | P11: =(Assumptions!$B$51+IF(Assumptions!$B$118=1,Assumptions!$B$52,0))*B11 | Q11: =MAX(Assumptions!$B$53*F11,Assumptions!$B$54*B11) | R11: =IF(AND(Assumptions!$B$120>0,A11>=2),MAX(Assumptions!$B$120*F11,Assumptions!$B$121),0) | S11: =J11+K11+L11+M11+N11+O11+P11+R11+Q11*Assumptions!$B$55+IF(Assumptions!$B$118=1,G11,0)+IF(Assumptions!$B$119=1,H11,0) | T11: =MAX(Assumptions!$B$58*F11-Assumptions!$B$59*S11,Assumptions!$B$60*F11) | U11: =Assumptions!$B$56+IF(A11>=13,Assumptions!$B$57/12,0) | V11: =SUM(G11:R11)+T11+U11 | W11: =F11-V11 | X11: =(CAPEX!$B$32+Assumptions!$B$122)/Assumptions!$B$68 | Y11: =W11-X11 | Z11: =W11 | AA11: =AA10+Z11 | AB11: =1/(1+((1+Assumptions!$B$6)^(1/12)-1))^A11 | AC11: =AC10+Z11*AB11
A12: 10 | B12: =(1+Assumptions!$B$4)^INT((A12-1)/12) | C12: =MIN(0.95,0.81*Assumptions!$B$114) | D12: =C12*Assumptions!$B$125 | E12: =Assumptions!$B$112*Assumptions!$B$113*B12 | F12: =D12*E12*Assumptions!$B$16 | G12: =MAX(Assumptions!$B$117*F12,Assumptions!$B$111*Assumptions!$B$32*B12) | H12: =Assumptions!$B$115*Assumptions!$B$116*B12 | I12: =(Assumptions!$B$124+Assumptions!$B$36)*B12 | J12: =MAX(Assumptions!$B$123*B12*D12*Assumptions!$B$16,Assumptions!$B$39*B12) | K12: =Assumptions!$B$40*B12 | L12: =Assumptions!$B$41*B12 | M12: =Assumptions!$B$42 | N12: =F12*Assumptions!$B$44*Assumptions!$B$45+Assumptions!$B$46 | O12: =IF(A12<=12,MAX(Assumptions!$B$47*F12,Assumptions!$B$48*B12),MAX(Assumptions!$B$49*F12,Assumptions!$B$50*B12)) | P12: =(Assumptions!$B$51+IF(Assumptions!$B$118=1,Assumptions!$B$52,0))*B12 | Q12: =MAX(Assumptions!$B$53*F12,Assumptions!$B$54*B12) | R12: =IF(AND(Assumptions!$B$120>0,A12>=2),MAX(Assumptions!$B$120*F12,Assumptions!$B$121),0) | S12: =J12+K12+L12+M12+N12+O12+P12+R12+Q12*Assumptions!$B$55+IF(Assumptions!$B$118=1,G12,0)+IF(Assumptions!$B$119=1,H12,0) | T12: =MAX(Assumptions!$B$58*F12-Assumptions!$B$59*S12,Assumptions!$B$60*F12) | U12: =Assumptions!$B$56+IF(A12>=13,Assumptions!$B$57/12,0) | V12: =SUM(G12:R12)+T12+U12 | W12: =F12-V12 | X12: =(CAPEX!$B$32+Assumptions!$B$122)/Assumptions!$B$68 | Y12: =W12-X12 | Z12: =W12 | AA12: =AA11+Z12 | AB12: =1/(1+((1+Assumptions!$B$6)^(1/12)-1))^A12 | AC12: =AC11+Z12*AB12
A13: 11 | B13: =(1+Assumptions!$B$4)^INT((A13-1)/12) | C13: =MIN(0.95,0.84*Assumptions!$B$114) | D13: =C13*Assumptions!$B$125 | E13: =Assumptions!$B$112*Assumptions!$B$113*B13 | F13: =D13*E13*Assumptions!$B$16 | G13: =MAX(Assumptions!$B$117*F13,Assumptions!$B$111*Assumptions!$B$32*B13) | H13: =Assumptions!$B$115*Assumptions!$B$116*B13 | I13: =(Assumptions!$B$124+Assumptions!$B$36)*B13 | J13: =MAX(Assumptions!$B$123*B13*D13*Assumptions!$B$16,Assumptions!$B$39*B13) | K13: =Assumptions!$B$40*B13 | L13: =Assumptions!$B$41*B13 | M13: =Assumptions!$B$42 | N13: =F13*Assumptions!$B$44*Assumptions!$B$45+Assumptions!$B$46 | O13: =IF(A13<=12,MAX(Assumptions!$B$47*F13,Assumptions!$B$48*B13),MAX(Assumptions!$B$49*F13,Assumptions!$B$50*B13)) | P13: =(Assumptions!$B$51+IF(Assumptions!$B$118=1,Assumptions!$B$52,0))*B13 | Q13: =MAX(Assumptions!$B$53*F13,Assumptions!$B$54*B13) | R13: =IF(AND(Assumptions!$B$120>0,A13>=2),MAX(Assumptions!$B$120*F13,Assumptions!$B$121),0) | S13: =J13+K13+L13+M13+N13+O13+P13+R13+Q13*Assumptions!$B$55+IF(Assumptions!$B$118=1,G13,0)+IF(Assumptions!$B$119=1,H13,0) | T13: =MAX(Assumptions!$B$58*F13-Assumptions!$B$59*S13,Assumptions!$B$60*F13) | U13: =Assumptions!$B$56+IF(A13>=13,Assumptions!$B$57/12,0) | V13: =SUM(G13:R13)+T13+U13 | W13: =F13-V13 | X13: =(CAPEX!$B$32+Assumptions!$B$122)/Assumptions!$B$68 | Y13: =W13-X13 | Z13: =W13 | AA13: =AA12+Z13 | AB13: =1/(1+((1+Assumptions!$B$6)^(1/12)-1))^A13 | AC13: =AC12+Z13*AB13
A14: 12 | B14: =(1+Assumptions!$B$4)^INT((A14-1)/12) | C14: =MIN(0.95,0.86*Assumptions!$B$114) | D14: =C14*Assumptions!$B$125 | E14: =Assumptions!$B$112*Assumptions!$B$113*B14 | F14: =D14*E14*Assumptions!$B$16 | G14: =MAX(Assumptions!$B$117*F14,Assumptions!$B$111*Assumptions!$B$32*B14) | H14: =Assumptions!$B$115*Assumptions!$B$116*B14 | I14: =(Assumptions!$B$124+Assumptions!$B$36)*B14 | J14: =MAX(Assumptions!$B$123*B14*D14*Assumptions!$B$16,Assumptions!$B$39*B14) | K14: =Assumptions!$B$40*B14 | L14: =Assumptions!$B$41*B14 | M14: =Assumptions!$B$42 | N14: =F14*Assumptions!$B$44*Assumptions!$B$45+Assumptions!$B$46 | O14: =IF(A14<=12,MAX(Assumptions!$B$47*F14,Assumptions!$B$48*B14),MAX(Assumptions!$B$49*F14,Assumptions!$B$50*B14)) | P14: =(Assumptions!$B$51+IF(Assumptions!$B$118=1,Assumptions!$B$52,0))*B14 | Q14: =MAX(Assumptions!$B$53*F14,Assumptions!$B$54*B14) | R14: =IF(AND(Assumptions!$B$120>0,A14>=2),MAX(Assumptions!$B$120*F14,Assumptions!$B$121),0) | S14: =J14+K14+L14+M14+N14+O14+P14+R14+Q14*Assumptions!$B$55+IF(Assumptions!$B$118=1,G14,0)+IF(Assumptions!$B$119=1,H14,0) | T14: =MAX(Assumptions!$B$58*F14-Assumptions!$B$59*S14,Assumptions!$B$60*F14) | U14: =Assumptions!$B$56+IF(A14>=13,Assumptions!$B$57/12,0) | V14: =SUM(G14:R14)+T14+U14 | W14: =F14-V14 | X14: =(CAPEX!$B$32+Assumptions!$B$122)/Assumptions!$B$68 | Y14: =W14-X14 | Z14: =W14 | AA14: =AA13+Z14 | AB14: =1/(1+((1+Assumptions!$B$6)^(1/12)-1))^A14 | AC14: =AC13+Z14*AB14
A15: 13 | B15: =(1+Assumptions!$B$4)^INT((A15-1)/12) | C15: =MIN(0.95,0.88*Assumptions!$B$114) | D15: =C15*Assumptions!$B$125 | E15: =Assumptions!$B$112*Assumptions!$B$113*B15 | F15: =D15*E15*Assumptions!$B$16 | G15: =MAX(Assumptions!$B$117*F15,Assumptions!$B$111*Assumptions!$B$32*B15) | H15: =Assumptions!$B$115*Assumptions!$B$116*B15 | I15: =(Assumptions!$B$124+Assumptions!$B$36)*B15 | J15: =MAX(Assumptions!$B$123*B15*D15*Assumptions!$B$16,Assumptions!$B$39*B15) | K15: =Assumptions!$B$40*B15 | L15: =Assumptions!$B$41*B15 | M15: =Assumptions!$B$42 | N15: =F15*Assumptions!$B$44*Assumptions!$B$45+Assumptions!$B$46 | O15: =IF(A15<=12,MAX(Assumptions!$B$47*F15,Assumptions!$B$48*B15),MAX(Assumptions!$B$49*F15,Assumptions!$B$50*B15)) | P15: =(Assumptions!$B$51+IF(Assumptions!$B$118=1,Assumptions!$B$52,0))*B15 | Q15: =MAX(Assumptions!$B$53*F15,Assumptions!$B$54*B15) | R15: =IF(AND(Assumptions!$B$120>0,A15>=2),MAX(Assumptions!$B$120*F15,Assumptions!$B$121),0) | S15: =J15+K15+L15+M15+N15+O15+P15+R15+Q15*Assumptions!$B$55+IF(Assumptions!$B$118=1,G15,0)+IF(Assumptions!$B$119=1,H15,0) | T15: =MAX(Assumptions!$B$58*F15-Assumptions!$B$59*S15,Assumptions!$B$60*F15) | U15: =Assumptions!$B$56+IF(A15>=13,Assumptions!$B$57/12,0) | V15: =SUM(G15:R15)+T15+U15 | W15: =F15-V15 | X15: =(CAPEX!$B$32+Assumptions!$B$122)/Assumptions!$B$68 | Y15: =W15-X15 | Z15: =W15 | AA15: =AA14+Z15 | AB15: =1/(1+((1+Assumptions!$B$6)^(1/12)-1))^A15 | AC15: =AC14+Z15*AB15
A16: 14 | B16: =(1+Assumptions!$B$4)^INT((A16-1)/12) | C16: =MIN(0.95,0.886364*Assumptions!$B$114) | D16: =C16*Assumptions!$B$125 | E16: =Assumptions!$B$112*Assumptions!$B$113*B16 | F16: =D16*E16*Assumptions!$B$16 | G16: =MAX(Assumptions!$B$117*F16,Assumptions!$B$111*Assumptions!$B$32*B16) | H16: =Assumptions!$B$115*Assumptions!$B$116*B16 | I16: =(Assumptions!$B$124+Assumptions!$B$36)*B16 | J16: =MAX(Assumptions!$B$123*B16*D16*Assumptions!$B$16,Assumptions!$B$39*B16) | K16: =Assumptions!$B$40*B16 | L16: =Assumptions!$B$41*B16 | M16: =Assumptions!$B$42 | N16: =F16*Assumptions!$B$44*Assumptions!$B$45+Assumptions!$B$46 | O16: =IF(A16<=12,MAX(Assumptions!$B$47*F16,Assumptions!$B$48*B16),MAX(Assumptions!$B$49*F16,Assumptions!$B$50*B16)) | P16: =(Assumptions!$B$51+IF(Assumptions!$B$118=1,Assumptions!$B$52,0))*B16 | Q16: =MAX(Assumptions!$B$53*F16,Assumptions!$B$54*B16) | R16: =IF(AND(Assumptions!$B$120>0,A16>=2),MAX(Assumptions!$B$120*F16,Assumptions!$B$121),0) | S16: =J16+K16+L16+M16+N16+O16+P16+R16+Q16*Assumptions!$B$55+IF(Assumptions!$B$118=1,G16,0)+IF(Assumptions!$B$119=1,H16,0) | T16: =MAX(Assumptions!$B$58*F16-Assumptions!$B$59*S16,Assumptions!$B$60*F16) | U16: =Assumptions!$B$56+IF(A16>=13,Assumptions!$B$57/12,0) | V16: =SUM(G16:R16)+T16+U16 | W16: =F16-V16 | X16: =(CAPEX!$B$32+Assumptions!$B$122)/Assumptions!$B$68 | Y16: =W16-X16 | Z16: =W16 | AA16: =AA15+Z16 | AB16: =1/(1+((1+Assumptions!$B$6)^(1/12)-1))^A16 | AC16: =AC15+Z16*AB16
A17: 15 | B17: =(1+Assumptions!$B$4)^INT((A17-1)/12) | C17: =MIN(0.95,0.892727*Assumptions!$B$114) | D17: =C17*Assumptions!$B$125 | E17: =Assumptions!$B$112*Assumptions!$B$113*B17 | F17: =D17*E17*Assumptions!$B$16 | G17: =MAX(Assumptions!$B$117*F17,Assumptions!$B$111*Assumptions!$B$32*B17) | H17: =Assumptions!$B$115*Assumptions!$B$116*B17 | I17: =(Assumptions!$B$124+Assumptions!$B$36)*B17 | J17: =MAX(Assumptions!$B$123*B17*D17*Assumptions!$B$16,Assumptions!$B$39*B17) | K17: =Assumptions!$B$40*B17 | L17: =Assumptions!$B$41*B17 | M17: =Assumptions!$B$42 | N17: =F17*Assumptions!$B$44*Assumptions!$B$45+Assumptions!$B$46 | O17: =IF(A17<=12,MAX(Assumptions!$B$47*F17,Assumptions!$B$48*B17),MAX(Assumptions!$B$49*F17,Assumptions!$B$50*B17)) | P17: =(Assumptions!$B$51+IF(Assumptions!$B$118=1,Assumptions!$B$52,0))*B17 | Q17: =MAX(Assumptions!$B$53*F17,Assumptions!$B$54*B17) | R17: =IF(AND(Assumptions!$B$120>0,A17>=2),MAX(Assumptions!$B$120*F17,Assumptions!$B$121),0) | S17: =J17+K17+L17+M17+N17+O17+P17+R17+Q17*Assumptions!$B$55+IF(Assumptions!$B$118=1,G17,0)+IF(Assumptions!$B$119=1,H17,0) | T17: =MAX(Assumptions!$B$58*F17-Assumptions!$B$59*S17,Assumptions!$B$60*F17) | U17: =Assumptions!$B$56+IF(A17>=13,Assumptions!$B$57/12,0) | V17: =SUM(G17:R17)+T17+U17 | W17: =F17-V17 | X17: =(CAPEX!$B$32+Assumptions!$B$122)/Assumptions!$B$68 | Y17: =W17-X17 | Z17: =W17 | AA17: =AA16+Z17 | AB17: =1/(1+((1+Assumptions!$B$6)^(1/12)-1))^A17 | AC17: =AC16+Z17*AB17
A18: 16 | B18: =(1+Assumptions!$B$4)^INT((A18-1)/12) | C18: =MIN(0.95,0.899091*Assumptions!$B$114) | D18: =C18*Assumptions!$B$125 | E18: =Assumptions!$B$112*Assumptions!$B$113*B18 | F18: =D18*E18*Assumptions!$B$16 | G18: =MAX(Assumptions!$B$117*F18,Assumptions!$B$111*Assumptions!$B$32*B18) | H18: =Assumptions!$B$115*Assumptions!$B$116*B18 | I18: =(Assumptions!$B$124+Assumptions!$B$36)*B18 | J18: =MAX(Assumptions!$B$123*B18*D18*Assumptions!$B$16,Assumptions!$B$39*B18) | K18: =Assumptions!$B$40*B18 | L18: =Assumptions!$B$41*B18 | M18: =Assumptions!$B$42 | N18: =F18*Assumptions!$B$44*Assumptions!$B$45+Assumptions!$B$46 | O18: =IF(A18<=12,MAX(Assumptions!$B$47*F18,Assumptions!$B$48*B18),MAX(Assumptions!$B$49*F18,Assumptions!$B$50*B18)) | P18: =(Assumptions!$B$51+IF(Assumptions!$B$118=1,Assumptions!$B$52,0))*B18 | Q18: =MAX(Assumptions!$B$53*F18,Assumptions!$B$54*B18) | R18: =IF(AND(Assumptions!$B$120>0,A18>=2),MAX(Assumptions!$B$120*F18,Assumptions!$B$121),0) | S18: =J18+K18+L18+M18+N18+O18+P18+R18+Q18*Assumptions!$B$55+IF(Assumptions!$B$118=1,G18,0)+IF(Assumptions!$B$119=1,H18,0) | T18: =MAX(Assumptions!$B$58*F18-Assumptions!$B$59*S18,Assumptions!$B$60*F18) | U18: =Assumptions!$B$56+IF(A18>=13,Assumptions!$B$57/12,0) | V18: =SUM(G18:R18)+T18+U18 | W18: =F18-V18 | X18: =(CAPEX!$B$32+Assumptions!$B$122)/Assumptions!$B$68 | Y18: =W18-X18 | Z18: =W18 | AA18: =AA17+Z18 | AB18: =1/(1+((1+Assumptions!$B$6)^(1/12)-1))^A18 | AC18: =AC17+Z18*AB18
A19: 17 | B19: =(1+Assumptions!$B$4)^INT((A19-1)/12) | C19: =MIN(0.95,0.905455*Assumptions!$B$114) | D19: =C19*Assumptions!$B$125 | E19: =Assumptions!$B$112*Assumptions!$B$113*B19 | F19: =D19*E19*Assumptions!$B$16 | G19: =MAX(Assumptions!$B$117*F19,Assumptions!$B$111*Assumptions!$B$32*B19) | H19: =Assumptions!$B$115*Assumptions!$B$116*B19 | I19: =(Assumptions!$B$124+Assumptions!$B$36)*B19 | J19: =MAX(Assumptions!$B$123*B19*D19*Assumptions!$B$16,Assumptions!$B$39*B19) | K19: =Assumptions!$B$40*B19 | L19: =Assumptions!$B$41*B19 | M19: =Assumptions!$B$42 | N19: =F19*Assumptions!$B$44*Assumptions!$B$45+Assumptions!$B$46 | O19: =IF(A19<=12,MAX(Assumptions!$B$47*F19,Assumptions!$B$48*B19),MAX(Assumptions!$B$49*F19,Assumptions!$B$50*B19)) | P19: =(Assumptions!$B$51+IF(Assumptions!$B$118=1,Assumptions!$B$52,0))*B19 | Q19: =MAX(Assumptions!$B$53*F19,Assumptions!$B$54*B19) | R19: =IF(AND(Assumptions!$B$120>0,A19>=2),MAX(Assumptions!$B$120*F19,Assumptions!$B$121),0) | S19: =J19+K19+L19+M19+N19+O19+P19+R19+Q19*Assumptions!$B$55+IF(Assumptions!$B$118=1,G19,0)+IF(Assumptions!$B$119=1,H19,0) | T19: =MAX(Assumptions!$B$58*F19-Assumptions!$B$59*S19,Assumptions!$B$60*F19) | U19: =Assumptions!$B$56+IF(A19>=13,Assumptions!$B$57/12,0) | V19: =SUM(G19:R19)+T19+U19 | W19: =F19-V19 | X19: =(CAPEX!$B$32+Assumptions!$B$122)/Assumptions!$B$68 | Y19: =W19-X19 | Z19: =W19 | AA19: =AA18+Z19 | AB19: =1/(1+((1+Assumptions!$B$6)^(1/12)-1))^A19 | AC19: =AC18+Z19*AB19
A20: 18 | B20: =(1+Assumptions!$B$4)^INT((A20-1)/12) | C20: =MIN(0.95,0.911818*Assumptions!$B$114) | D20: =C20*Assumptions!$B$125 | E20: =Assumptions!$B$112*Assumptions!$B$113*B20 | F20: =D20*E20*Assumptions!$B$16 | G20: =MAX(Assumptions!$B$117*F20,Assumptions!$B$111*Assumptions!$B$32*B20) | H20: =Assumptions!$B$115*Assumptions!$B$116*B20 | I20: =(Assumptions!$B$124+Assumptions!$B$36)*B20 | J20: =MAX(Assumptions!$B$123*B20*D20*Assumptions!$B$16,Assumptions!$B$39*B20) | K20: =Assumptions!$B$40*B20 | L20: =Assumptions!$B$41*B20 | M20: =Assumptions!$B$42 | N20: =F20*Assumptions!$B$44*Assumptions!$B$45+Assumptions!$B$46 | O20: =IF(A20<=12,MAX(Assumptions!$B$47*F20,Assumptions!$B$48*B20),MAX(Assumptions!$B$49*F20,Assumptions!$B$50*B20)) | P20: =(Assumptions!$B$51+IF(Assumptions!$B$118=1,Assumptions!$B$52,0))*B20 | Q20: =MAX(Assumptions!$B$53*F20,Assumptions!$B$54*B20) | R20: =IF(AND(Assumptions!$B$120>0,A20>=2),MAX(Assumptions!$B$120*F20,Assumptions!$B$121),0) | S20: =J20+K20+L20+M20+N20+O20+P20+R20+Q20*Assumptions!$B$55+IF(Assumptions!$B$118=1,G20,0)+IF(Assumptions!$B$119=1,H20,0) | T20: =MAX(Assumptions!$B$58*F20-Assumptions!$B$59*S20,Assumptions!$B$60*F20) | U20: =Assumptions!$B$56+IF(A20>=13,Assumptions!$B$57/12,0) | V20: =SUM(G20:R20)+T20+U20 | W20: =F20-V20 | X20: =(CAPEX!$B$32+Assumptions!$B$122)/Assumptions!$B$68 | Y20: =W20-X20 | Z20: =W20 | AA20: =AA19+Z20 | AB20: =1/(1+((1+Assumptions!$B$6)^(1/12)-1))^A20 | AC20: =AC19+Z20*AB20
A21: 19 | B21: =(1+Assumptions!$B$4)^INT((A21-1)/12) | C21: =MIN(0.95,0.918182*Assumptions!$B$114) | D21: =C21*Assumptions!$B$125 | E21: =Assumptions!$B$112*Assumptions!$B$113*B21 | F21: =D21*E21*Assumptions!$B$16 | G21: =MAX(Assumptions!$B$117*F21,Assumptions!$B$111*Assumptions!$B$32*B21) | H21: =Assumptions!$B$115*Assumptions!$B$116*B21 | I21: =(Assumptions!$B$124+Assumptions!$B$36)*B21 | J21: =MAX(Assumptions!$B$123*B21*D21*Assumptions!$B$16,Assumptions!$B$39*B21) | K21: =Assumptions!$B$40*B21 | L21: =Assumptions!$B$41*B21 | M21: =Assumptions!$B$42 | N21: =F21*Assumptions!$B$44*Assumptions!$B$45+Assumptions!$B$46 | O21: =IF(A21<=12,MAX(Assumptions!$B$47*F21,Assumptions!$B$48*B21),MAX(Assumptions!$B$49*F21,Assumptions!$B$50*B21)) | P21: =(Assumptions!$B$51+IF(Assumptions!$B$118=1,Assumptions!$B$52,0))*B21 | Q21: =MAX(Assumptions!$B$53*F21,Assumptions!$B$54*B21) | R21: =IF(AND(Assumptions!$B$120>0,A21>=2),MAX(Assumptions!$B$120*F21,Assumptions!$B$121),0) | S21: =J21+K21+L21+M21+N21+O21+P21+R21+Q21*Assumptions!$B$55+IF(Assumptions!$B$118=1,G21,0)+IF(Assumptions!$B$119=1,H21,0) | T21: =MAX(Assumptions!$B$58*F21-Assumptions!$B$59*S21,Assumptions!$B$60*F21) | U21: =Assumptions!$B$56+IF(A21>=13,Assumptions!$B$57/12,0) | V21: =SUM(G21:R21)+T21+U21 | W21: =F21-V21 | X21: =(CAPEX!$B$32+Assumptions!$B$122)/Assumptions!$B$68 | Y21: =W21-X21 | Z21: =W21 | AA21: =AA20+Z21 | AB21: =1/(1+((1+Assumptions!$B$6)^(1/12)-1))^A21 | AC21: =AC20+Z21*AB21
A22: 20 | B22: =(1+Assumptions!$B$4)^INT((A22-1)/12) | C22: =MIN(0.95,0.924545*Assumptions!$B$114) | D22: =C22*Assumptions!$B$125 | E22: =Assumptions!$B$112*Assumptions!$B$113*B22 | F22: =D22*E22*Assumptions!$B$16 | G22: =MAX(Assumptions!$B$117*F22,Assumptions!$B$111*Assumptions!$B$32*B22) | H22: =Assumptions!$B$115*Assumptions!$B$116*B22 | I22: =(Assumptions!$B$124+Assumptions!$B$36)*B22 | J22: =MAX(Assumptions!$B$123*B22*D22*Assumptions!$B$16,Assumptions!$B$39*B22) | K22: =Assumptions!$B$40*B22 | L22: =Assumptions!$B$41*B22 | M22: =Assumptions!$B$42 | N22: =F22*Assumptions!$B$44*Assumptions!$B$45+Assumptions!$B$46 | O22: =IF(A22<=12,MAX(Assumptions!$B$47*F22,Assumptions!$B$48*B22),MAX(Assumptions!$B$49*F22,Assumptions!$B$50*B22)) | P22: =(Assumptions!$B$51+IF(Assumptions!$B$118=1,Assumptions!$B$52,0))*B22 | Q22: =MAX(Assumptions!$B$53*F22,Assumptions!$B$54*B22) | R22: =IF(AND(Assumptions!$B$120>0,A22>=2),MAX(Assumptions!$B$120*F22,Assumptions!$B$121),0) | S22: =J22+K22+L22+M22+N22+O22+P22+R22+Q22*Assumptions!$B$55+IF(Assumptions!$B$118=1,G22,0)+IF(Assumptions!$B$119=1,H22,0) | T22: =MAX(Assumptions!$B$58*F22-Assumptions!$B$59*S22,Assumptions!$B$60*F22) | U22: =Assumptions!$B$56+IF(A22>=13,Assumptions!$B$57/12,0) | V22: =SUM(G22:R22)+T22+U22 | W22: =F22-V22 | X22: =(CAPEX!$B$32+Assumptions!$B$122)/Assumptions!$B$68 | Y22: =W22-X22 | Z22: =W22 | AA22: =AA21+Z22 | AB22: =1/(1+((1+Assumptions!$B$6)^(1/12)-1))^A22 | AC22: =AC21+Z22*AB22
A23: 21 | B23: =(1+Assumptions!$B$4)^INT((A23-1)/12) | C23: =MIN(0.95,0.930909*Assumptions!$B$114) | D23: =C23*Assumptions!$B$125 | E23: =Assumptions!$B$112*Assumptions!$B$113*B23 | F23: =D23*E23*Assumptions!$B$16 | G23: =MAX(Assumptions!$B$117*F23,Assumptions!$B$111*Assumptions!$B$32*B23) | H23: =Assumptions!$B$115*Assumptions!$B$116*B23 | I23: =(Assumptions!$B$124+Assumptions!$B$36)*B23 | J23: =MAX(Assumptions!$B$123*B23*D23*Assumptions!$B$16,Assumptions!$B$39*B23) | K23: =Assumptions!$B$40*B23 | L23: =Assumptions!$B$41*B23 | M23: =Assumptions!$B$42 | N23: =F23*Assumptions!$B$44*Assumptions!$B$45+Assumptions!$B$46 | O23: =IF(A23<=12,MAX(Assumptions!$B$47*F23,Assumptions!$B$48*B23),MAX(Assumptions!$B$49*F23,Assumptions!$B$50*B23)) | P23: =(Assumptions!$B$51+IF(Assumptions!$B$118=1,Assumptions!$B$52,0))*B23 | Q23: =MAX(Assumptions!$B$53*F23,Assumptions!$B$54*B23) | R23: =IF(AND(Assumptions!$B$120>0,A23>=2),MAX(Assumptions!$B$120*F23,Assumptions!$B$121),0) | S23: =J23+K23+L23+M23+N23+O23+P23+R23+Q23*Assumptions!$B$55+IF(Assumptions!$B$118=1,G23,0)+IF(Assumptions!$B$119=1,H23,0) | T23: =MAX(Assumptions!$B$58*F23-Assumptions!$B$59*S23,Assumptions!$B$60*F23) | U23: =Assumptions!$B$56+IF(A23>=13,Assumptions!$B$57/12,0) | V23: =SUM(G23:R23)+T23+U23 | W23: =F23-V23 | X23: =(CAPEX!$B$32+Assumptions!$B$122)/Assumptions!$B$68 | Y23: =W23-X23 | Z23: =W23 | AA23: =AA22+Z23 | AB23: =1/(1+((1+Assumptions!$B$6)^(1/12)-1))^A23 | AC23: =AC22+Z23*AB23
A24: 22 | B24: =(1+Assumptions!$B$4)^INT((A24-1)/12) | C24: =MIN(0.95,0.937273*Assumptions!$B$114) | D24: =C24*Assumptions!$B$125 | E24: =Assumptions!$B$112*Assumptions!$B$113*B24 | F24: =D24*E24*Assumptions!$B$16 | G24: =MAX(Assumptions!$B$117*F24,Assumptions!$B$111*Assumptions!$B$32*B24) | H24: =Assumptions!$B$115*Assumptions!$B$116*B24 | I24: =(Assumptions!$B$124+Assumptions!$B$36)*B24 | J24: =MAX(Assumptions!$B$123*B24*D24*Assumptions!$B$16,Assumptions!$B$39*B24) | K24: =Assumptions!$B$40*B24 | L24: =Assumptions!$B$41*B24 | M24: =Assumptions!$B$42 | N24: =F24*Assumptions!$B$44*Assumptions!$B$45+Assumptions!$B$46 | O24: =IF(A24<=12,MAX(Assumptions!$B$47*F24,Assumptions!$B$48*B24),MAX(Assumptions!$B$49*F24,Assumptions!$B$50*B24)) | P24: =(Assumptions!$B$51+IF(Assumptions!$B$118=1,Assumptions!$B$52,0))*B24 | Q24: =MAX(Assumptions!$B$53*F24,Assumptions!$B$54*B24) | R24: =IF(AND(Assumptions!$B$120>0,A24>=2),MAX(Assumptions!$B$120*F24,Assumptions!$B$121),0) | S24: =J24+K24+L24+M24+N24+O24+P24+R24+Q24*Assumptions!$B$55+IF(Assumptions!$B$118=1,G24,0)+IF(Assumptions!$B$119=1,H24,0) | T24: =MAX(Assumptions!$B$58*F24-Assumptions!$B$59*S24,Assumptions!$B$60*F24) | U24: =Assumptions!$B$56+IF(A24>=13,Assumptions!$B$57/12,0) | V24: =SUM(G24:R24)+T24+U24 | W24: =F24-V24 | X24: =(CAPEX!$B$32+Assumptions!$B$122)/Assumptions!$B$68 | Y24: =W24-X24 | Z24: =W24 | AA24: =AA23+Z24 | AB24: =1/(1+((1+Assumptions!$B$6)^(1/12)-1))^A24 | AC24: =AC23+Z24*AB24
A25: 23 | B25: =(1+Assumptions!$B$4)^INT((A25-1)/12) | C25: =MIN(0.95,0.943636*Assumptions!$B$114) | D25: =C25*Assumptions!$B$125 | E25: =Assumptions!$B$112*Assumptions!$B$113*B25 | F25: =D25*E25*Assumptions!$B$16 | G25: =MAX(Assumptions!$B$117*F25,Assumptions!$B$111*Assumptions!$B$32*B25) | H25: =Assumptions!$B$115*Assumptions!$B$116*B25 | I25: =(Assumptions!$B$124+Assumptions!$B$36)*B25 | J25: =MAX(Assumptions!$B$123*B25*D25*Assumptions!$B$16,Assumptions!$B$39*B25) | K25: =Assumptions!$B$40*B25 | L25: =Assumptions!$B$41*B25 | M25: =Assumptions!$B$42 | N25: =F25*Assumptions!$B$44*Assumptions!$B$45+Assumptions!$B$46 | O25: =IF(A25<=12,MAX(Assumptions!$B$47*F25,Assumptions!$B$48*B25),MAX(Assumptions!$B$49*F25,Assumptions!$B$50*B25)) | P25: =(Assumptions!$B$51+IF(Assumptions!$B$118=1,Assumptions!$B$52,0))*B25 | Q25: =MAX(Assumptions!$B$53*F25,Assumptions!$B$54*B25) | R25: =IF(AND(Assumptions!$B$120>0,A25>=2),MAX(Assumptions!$B$120*F25,Assumptions!$B$121),0) | S25: =J25+K25+L25+M25+N25+O25+P25+R25+Q25*Assumptions!$B$55+IF(Assumptions!$B$118=1,G25,0)+IF(Assumptions!$B$119=1,H25,0) | T25: =MAX(Assumptions!$B$58*F25-Assumptions!$B$59*S25,Assumptions!$B$60*F25) | U25: =Assumptions!$B$56+IF(A25>=13,Assumptions!$B$57/12,0) | V25: =SUM(G25:R25)+T25+U25 | W25: =F25-V25 | X25: =(CAPEX!$B$32+Assumptions!$B$122)/Assumptions!$B$68 | Y25: =W25-X25 | Z25: =W25 | AA25: =AA24+Z25 | AB25: =1/(1+((1+Assumptions!$B$6)^(1/12)-1))^A25 | AC25: =AC24+Z25*AB25
A26: 24 | B26: =(1+Assumptions!$B$4)^INT((A26-1)/12) | C26: =MIN(0.95,0.95*Assumptions!$B$114) | D26: =C26*Assumptions!$B$125 | E26: =Assumptions!$B$112*Assumptions!$B$113*B26 | F26: =D26*E26*Assumptions!$B$16 | G26: =MAX(Assumptions!$B$117*F26,Assumptions!$B$111*Assumptions!$B$32*B26) | H26: =Assumptions!$B$115*Assumptions!$B$116*B26 | I26: =(Assumptions!$B$124+Assumptions!$B$36)*B26 | J26: =MAX(Assumptions!$B$123*B26*D26*Assumptions!$B$16,Assumptions!$B$39*B26) | K26: =Assumptions!$B$40*B26 | L26: =Assumptions!$B$41*B26 | M26: =Assumptions!$B$42 | N26: =F26*Assumptions!$B$44*Assumptions!$B$45+Assumptions!$B$46 | O26: =IF(A26<=12,MAX(Assumptions!$B$47*F26,Assumptions!$B$48*B26),MAX(Assumptions!$B$49*F26,Assumptions!$B$50*B26)) | P26: =(Assumptions!$B$51+IF(Assumptions!$B$118=1,Assumptions!$B$52,0))*B26 | Q26: =MAX(Assumptions!$B$53*F26,Assumptions!$B$54*B26) | R26: =IF(AND(Assumptions!$B$120>0,A26>=2),MAX(Assumptions!$B$120*F26,Assumptions!$B$121),0) | S26: =J26+K26+L26+M26+N26+O26+P26+R26+Q26*Assumptions!$B$55+IF(Assumptions!$B$118=1,G26,0)+IF(Assumptions!$B$119=1,H26,0) | T26: =MAX(Assumptions!$B$58*F26-Assumptions!$B$59*S26,Assumptions!$B$60*F26) | U26: =Assumptions!$B$56+IF(A26>=13,Assumptions!$B$57/12,0) | V26: =SUM(G26:R26)+T26+U26 | W26: =F26-V26 | X26: =(CAPEX!$B$32+Assumptions!$B$122)/Assumptions!$B$68 | Y26: =W26-X26 | Z26: =W26 | AA26: =AA25+Z26 | AB26: =1/(1+((1+Assumptions!$B$6)^(1/12)-1))^A26 | AC26: =AC25+Z26*AB26
A27: 25 | B27: =(1+Assumptions!$B$4)^INT((A27-1)/12) | C27: =MIN(0.95,0.97*Assumptions!$B$114) | D27: =C27*Assumptions!$B$125 | E27: =Assumptions!$B$112*Assumptions!$B$113*B27 | F27: =D27*E27*Assumptions!$B$16 | G27: =MAX(Assumptions!$B$117*F27,Assumptions!$B$111*Assumptions!$B$32*B27) | H27: =Assumptions!$B$115*Assumptions!$B$116*B27 | I27: =(Assumptions!$B$124+Assumptions!$B$36)*B27 | J27: =MAX(Assumptions!$B$123*B27*D27*Assumptions!$B$16,Assumptions!$B$39*B27) | K27: =Assumptions!$B$40*B27 | L27: =Assumptions!$B$41*B27 | M27: =Assumptions!$B$42 | N27: =F27*Assumptions!$B$44*Assumptions!$B$45+Assumptions!$B$46 | O27: =IF(A27<=12,MAX(Assumptions!$B$47*F27,Assumptions!$B$48*B27),MAX(Assumptions!$B$49*F27,Assumptions!$B$50*B27)) | P27: =(Assumptions!$B$51+IF(Assumptions!$B$118=1,Assumptions!$B$52,0))*B27 | Q27: =MAX(Assumptions!$B$53*F27,Assumptions!$B$54*B27) | R27: =IF(AND(Assumptions!$B$120>0,A27>=2),MAX(Assumptions!$B$120*F27,Assumptions!$B$121),0) | S27: =J27+K27+L27+M27+N27+O27+P27+R27+Q27*Assumptions!$B$55+IF(Assumptions!$B$118=1,G27,0)+IF(Assumptions!$B$119=1,H27,0) | T27: =MAX(Assumptions!$B$58*F27-Assumptions!$B$59*S27,Assumptions!$B$60*F27) | U27: =Assumptions!$B$56+IF(A27>=13,Assumptions!$B$57/12,0) | V27: =SUM(G27:R27)+T27+U27 | W27: =F27-V27 | X27: =(CAPEX!$B$32+Assumptions!$B$122)/Assumptions!$B$68 | Y27: =W27-X27 | Z27: =W27 | AA27: =AA26+Z27 | AB27: =1/(1+((1+Assumptions!$B$6)^(1/12)-1))^A27 | AC27: =AC26+Z27*AB27
A28: 26 | B28: =(1+Assumptions!$B$4)^INT((A28-1)/12) | C28: =MIN(0.95,0.972727*Assumptions!$B$114) | D28: =C28*Assumptions!$B$125 | E28: =Assumptions!$B$112*Assumptions!$B$113*B28 | F28: =D28*E28*Assumptions!$B$16 | G28: =MAX(Assumptions!$B$117*F28,Assumptions!$B$111*Assumptions!$B$32*B28) | H28: =Assumptions!$B$115*Assumptions!$B$116*B28 | I28: =(Assumptions!$B$124+Assumptions!$B$36)*B28 | J28: =MAX(Assumptions!$B$123*B28*D28*Assumptions!$B$16,Assumptions!$B$39*B28) | K28: =Assumptions!$B$40*B28 | L28: =Assumptions!$B$41*B28 | M28: =Assumptions!$B$42 | N28: =F28*Assumptions!$B$44*Assumptions!$B$45+Assumptions!$B$46 | O28: =IF(A28<=12,MAX(Assumptions!$B$47*F28,Assumptions!$B$48*B28),MAX(Assumptions!$B$49*F28,Assumptions!$B$50*B28)) | P28: =(Assumptions!$B$51+IF(Assumptions!$B$118=1,Assumptions!$B$52,0))*B28 | Q28: =MAX(Assumptions!$B$53*F28,Assumptions!$B$54*B28) | R28: =IF(AND(Assumptions!$B$120>0,A28>=2),MAX(Assumptions!$B$120*F28,Assumptions!$B$121),0) | S28: =J28+K28+L28+M28+N28+O28+P28+R28+Q28*Assumptions!$B$55+IF(Assumptions!$B$118=1,G28,0)+IF(Assumptions!$B$119=1,H28,0) | T28: =MAX(Assumptions!$B$58*F28-Assumptions!$B$59*S28,Assumptions!$B$60*F28) | U28: =Assumptions!$B$56+IF(A28>=13,Assumptions!$B$57/12,0) | V28: =SUM(G28:R28)+T28+U28 | W28: =F28-V28 | X28: =(CAPEX!$B$32+Assumptions!$B$122)/Assumptions!$B$68 | Y28: =W28-X28 | Z28: =W28 | AA28: =AA27+Z28 | AB28: =1/(1+((1+Assumptions!$B$6)^(1/12)-1))^A28 | AC28: =AC27+Z28*AB28
A29: 27 | B29: =(1+Assumptions!$B$4)^INT((A29-1)/12) | C29: =MIN(0.95,0.975455*Assumptions!$B$114) | D29: =C29*Assumptions!$B$125 | E29: =Assumptions!$B$112*Assumptions!$B$113*B29 | F29: =D29*E29*Assumptions!$B$16 | G29: =MAX(Assumptions!$B$117*F29,Assumptions!$B$111*Assumptions!$B$32*B29) | H29: =Assumptions!$B$115*Assumptions!$B$116*B29 | I29: =(Assumptions!$B$124+Assumptions!$B$36)*B29 | J29: =MAX(Assumptions!$B$123*B29*D29*Assumptions!$B$16,Assumptions!$B$39*B29) | K29: =Assumptions!$B$40*B29 | L29: =Assumptions!$B$41*B29 | M29: =Assumptions!$B$42 | N29: =F29*Assumptions!$B$44*Assumptions!$B$45+Assumptions!$B$46 | O29: =IF(A29<=12,MAX(Assumptions!$B$47*F29,Assumptions!$B$48*B29),MAX(Assumptions!$B$49*F29,Assumptions!$B$50*B29)) | P29: =(Assumptions!$B$51+IF(Assumptions!$B$118=1,Assumptions!$B$52,0))*B29 | Q29: =MAX(Assumptions!$B$53*F29,Assumptions!$B$54*B29) | R29: =IF(AND(Assumptions!$B$120>0,A29>=2),MAX(Assumptions!$B$120*F29,Assumptions!$B$121),0) | S29: =J29+K29+L29+M29+N29+O29+P29+R29+Q29*Assumptions!$B$55+IF(Assumptions!$B$118=1,G29,0)+IF(Assumptions!$B$119=1,H29,0) | T29: =MAX(Assumptions!$B$58*F29-Assumptions!$B$59*S29,Assumptions!$B$60*F29) | U29: =Assumptions!$B$56+IF(A29>=13,Assumptions!$B$57/12,0) | V29: =SUM(G29:R29)+T29+U29 | W29: =F29-V29 | X29: =(CAPEX!$B$32+Assumptions!$B$122)/Assumptions!$B$68 | Y29: =W29-X29 | Z29: =W29 | AA29: =AA28+Z29 | AB29: =1/(1+((1+Assumptions!$B$6)^(1/12)-1))^A29 | AC29: =AC28+Z29*AB29
A30: 28 | B30: =(1+Assumptions!$B$4)^INT((A30-1)/12) | C30: =MIN(0.95,0.978182*Assumptions!$B$114) | D30: =C30*Assumptions!$B$125 | E30: =Assumptions!$B$112*Assumptions!$B$113*B30 | F30: =D30*E30*Assumptions!$B$16 | G30: =MAX(Assumptions!$B$117*F30,Assumptions!$B$111*Assumptions!$B$32*B30) | H30: =Assumptions!$B$115*Assumptions!$B$116*B30 | I30: =(Assumptions!$B$124+Assumptions!$B$36)*B30 | J30: =MAX(Assumptions!$B$123*B30*D30*Assumptions!$B$16,Assumptions!$B$39*B30) | K30: =Assumptions!$B$40*B30 | L30: =Assumptions!$B$41*B30 | M30: =Assumptions!$B$42 | N30: =F30*Assumptions!$B$44*Assumptions!$B$45+Assumptions!$B$46 | O30: =IF(A30<=12,MAX(Assumptions!$B$47*F30,Assumptions!$B$48*B30),MAX(Assumptions!$B$49*F30,Assumptions!$B$50*B30)) | P30: =(Assumptions!$B$51+IF(Assumptions!$B$118=1,Assumptions!$B$52,0))*B30 | Q30: =MAX(Assumptions!$B$53*F30,Assumptions!$B$54*B30) | R30: =IF(AND(Assumptions!$B$120>0,A30>=2),MAX(Assumptions!$B$120*F30,Assumptions!$B$121),0) | S30: =J30+K30+L30+M30+N30+O30+P30+R30+Q30*Assumptions!$B$55+IF(Assumptions!$B$118=1,G30,0)+IF(Assumptions!$B$119=1,H30,0) | T30: =MAX(Assumptions!$B$58*F30-Assumptions!$B$59*S30,Assumptions!$B$60*F30) | U30: =Assumptions!$B$56+IF(A30>=13,Assumptions!$B$57/12,0) | V30: =SUM(G30:R30)+T30+U30 | W30: =F30-V30 | X30: =(CAPEX!$B$32+Assumptions!$B$122)/Assumptions!$B$68 | Y30: =W30-X30 | Z30: =W30 | AA30: =AA29+Z30 | AB30: =1/(1+((1+Assumptions!$B$6)^(1/12)-1))^A30 | AC30: =AC29+Z30*AB30
A31: 29 | B31: =(1+Assumptions!$B$4)^INT((A31-1)/12) | C31: =MIN(0.95,0.980909*Assumptions!$B$114) | D31: =C31*Assumptions!$B$125 | E31: =Assumptions!$B$112*Assumptions!$B$113*B31 | F31: =D31*E31*Assumptions!$B$16 | G31: =MAX(Assumptions!$B$117*F31,Assumptions!$B$111*Assumptions!$B$32*B31) | H31: =Assumptions!$B$115*Assumptions!$B$116*B31 | I31: =(Assumptions!$B$124+Assumptions!$B$36)*B31 | J31: =MAX(Assumptions!$B$123*B31*D31*Assumptions!$B$16,Assumptions!$B$39*B31) | K31: =Assumptions!$B$40*B31 | L31: =Assumptions!$B$41*B31 | M31: =Assumptions!$B$42 | N31: =F31*Assumptions!$B$44*Assumptions!$B$45+Assumptions!$B$46 | O31: =IF(A31<=12,MAX(Assumptions!$B$47*F31,Assumptions!$B$48*B31),MAX(Assumptions!$B$49*F31,Assumptions!$B$50*B31)) | P31: =(Assumptions!$B$51+IF(Assumptions!$B$118=1,Assumptions!$B$52,0))*B31 | Q31: =MAX(Assumptions!$B$53*F31,Assumptions!$B$54*B31) | R31: =IF(AND(Assumptions!$B$120>0,A31>=2),MAX(Assumptions!$B$120*F31,Assumptions!$B$121),0) | S31: =J31+K31+L31+M31+N31+O31+P31+R31+Q31*Assumptions!$B$55+IF(Assumptions!$B$118=1,G31,0)+IF(Assumptions!$B$119=1,H31,0) | T31: =MAX(Assumptions!$B$58*F31-Assumptions!$B$59*S31,Assumptions!$B$60*F31) | U31: =Assumptions!$B$56+IF(A31>=13,Assumptions!$B$57/12,0) | V31: =SUM(G31:R31)+T31+U31 | W31: =F31-V31 | X31: =(CAPEX!$B$32+Assumptions!$B$122)/Assumptions!$B$68 | Y31: =W31-X31 | Z31: =W31 | AA31: =AA30+Z31 | AB31: =1/(1+((1+Assumptions!$B$6)^(1/12)-1))^A31 | AC31: =AC30+Z31*AB31
A32: 30 | B32: =(1+Assumptions!$B$4)^INT((A32-1)/12) | C32: =MIN(0.95,0.983636*Assumptions!$B$114) | D32: =C32*Assumptions!$B$125 | E32: =Assumptions!$B$112*Assumptions!$B$113*B32 | F32: =D32*E32*Assumptions!$B$16 | G32: =MAX(Assumptions!$B$117*F32,Assumptions!$B$111*Assumptions!$B$32*B32) | H32: =Assumptions!$B$115*Assumptions!$B$116*B32 | I32: =(Assumptions!$B$124+Assumptions!$B$36)*B32 | J32: =MAX(Assumptions!$B$123*B32*D32*Assumptions!$B$16,Assumptions!$B$39*B32) | K32: =Assumptions!$B$40*B32 | L32: =Assumptions!$B$41*B32 | M32: =Assumptions!$B$42 | N32: =F32*Assumptions!$B$44*Assumptions!$B$45+Assumptions!$B$46 | O32: =IF(A32<=12,MAX(Assumptions!$B$47*F32,Assumptions!$B$48*B32),MAX(Assumptions!$B$49*F32,Assumptions!$B$50*B32)) | P32: =(Assumptions!$B$51+IF(Assumptions!$B$118=1,Assumptions!$B$52,0))*B32 | Q32: =MAX(Assumptions!$B$53*F32,Assumptions!$B$54*B32) | R32: =IF(AND(Assumptions!$B$120>0,A32>=2),MAX(Assumptions!$B$120*F32,Assumptions!$B$121),0) | S32: =J32+K32+L32+M32+N32+O32+P32+R32+Q32*Assumptions!$B$55+IF(Assumptions!$B$118=1,G32,0)+IF(Assumptions!$B$119=1,H32,0) | T32: =MAX(Assumptions!$B$58*F32-Assumptions!$B$59*S32,Assumptions!$B$60*F32) | U32: =Assumptions!$B$56+IF(A32>=13,Assumptions!$B$57/12,0) | V32: =SUM(G32:R32)+T32+U32 | W32: =F32-V32 | X32: =(CAPEX!$B$32+Assumptions!$B$122)/Assumptions!$B$68 | Y32: =W32-X32 | Z32: =W32 | AA32: =AA31+Z32 | AB32: =1/(1+((1+Assumptions!$B$6)^(1/12)-1))^A32 | AC32: =AC31+Z32*AB32
A33: 31 | B33: =(1+Assumptions!$B$4)^INT((A33-1)/12) | C33: =MIN(0.95,0.986364*Assumptions!$B$114) | D33: =C33*Assumptions!$B$125 | E33: =Assumptions!$B$112*Assumptions!$B$113*B33 | F33: =D33*E33*Assumptions!$B$16 | G33: =MAX(Assumptions!$B$117*F33,Assumptions!$B$111*Assumptions!$B$32*B33) | H33: =Assumptions!$B$115*Assumptions!$B$116*B33 | I33: =(Assumptions!$B$124+Assumptions!$B$36)*B33 | J33: =MAX(Assumptions!$B$123*B33*D33*Assumptions!$B$16,Assumptions!$B$39*B33) | K33: =Assumptions!$B$40*B33 | L33: =Assumptions!$B$41*B33 | M33: =Assumptions!$B$42 | N33: =F33*Assumptions!$B$44*Assumptions!$B$45+Assumptions!$B$46 | O33: =IF(A33<=12,MAX(Assumptions!$B$47*F33,Assumptions!$B$48*B33),MAX(Assumptions!$B$49*F33,Assumptions!$B$50*B33)) | P33: =(Assumptions!$B$51+IF(Assumptions!$B$118=1,Assumptions!$B$52,0))*B33 | Q33: =MAX(Assumptions!$B$53*F33,Assumptions!$B$54*B33) | R33: =IF(AND(Assumptions!$B$120>0,A33>=2),MAX(Assumptions!$B$120*F33,Assumptions!$B$121),0) | S33: =J33+K33+L33+M33+N33+O33+P33+R33+Q33*Assumptions!$B$55+IF(Assumptions!$B$118=1,G33,0)+IF(Assumptions!$B$119=1,H33,0) | T33: =MAX(Assumptions!$B$58*F33-Assumptions!$B$59*S33,Assumptions!$B$60*F33) | U33: =Assumptions!$B$56+IF(A33>=13,Assumptions!$B$57/12,0) | V33: =SUM(G33:R33)+T33+U33 | W33: =F33-V33 | X33: =(CAPEX!$B$32+Assumptions!$B$122)/Assumptions!$B$68 | Y33: =W33-X33 | Z33: =W33 | AA33: =AA32+Z33 | AB33: =1/(1+((1+Assumptions!$B$6)^(1/12)-1))^A33 | AC33: =AC32+Z33*AB33
A34: 32 | B34: =(1+Assumptions!$B$4)^INT((A34-1)/12) | C34: =MIN(0.95,0.989091*Assumptions!$B$114) | D34: =C34*Assumptions!$B$125 | E34: =Assumptions!$B$112*Assumptions!$B$113*B34 | F34: =D34*E34*Assumptions!$B$16 | G34: =MAX(Assumptions!$B$117*F34,Assumptions!$B$111*Assumptions!$B$32*B34) | H34: =Assumptions!$B$115*Assumptions!$B$116*B34 | I34: =(Assumptions!$B$124+Assumptions!$B$36)*B34 | J34: =MAX(Assumptions!$B$123*B34*D34*Assumptions!$B$16,Assumptions!$B$39*B34) | K34: =Assumptions!$B$40*B34 | L34: =Assumptions!$B$41*B34 | M34: =Assumptions!$B$42 | N34: =F34*Assumptions!$B$44*Assumptions!$B$45+Assumptions!$B$46 | O34: =IF(A34<=12,MAX(Assumptions!$B$47*F34,Assumptions!$B$48*B34),MAX(Assumptions!$B$49*F34,Assumptions!$B$50*B34)) | P34: =(Assumptions!$B$51+IF(Assumptions!$B$118=1,Assumptions!$B$52,0))*B34 | Q34: =MAX(Assumptions!$B$53*F34,Assumptions!$B$54*B34) | R34: =IF(AND(Assumptions!$B$120>0,A34>=2),MAX(Assumptions!$B$120*F34,Assumptions!$B$121),0) | S34: =J34+K34+L34+M34+N34+O34+P34+R34+Q34*Assumptions!$B$55+IF(Assumptions!$B$118=1,G34,0)+IF(Assumptions!$B$119=1,H34,0) | T34: =MAX(Assumptions!$B$58*F34-Assumptions!$B$59*S34,Assumptions!$B$60*F34) | U34: =Assumptions!$B$56+IF(A34>=13,Assumptions!$B$57/12,0) | V34: =SUM(G34:R34)+T34+U34 | W34: =F34-V34 | X34: =(CAPEX!$B$32+Assumptions!$B$122)/Assumptions!$B$68 | Y34: =W34-X34 | Z34: =W34 | AA34: =AA33+Z34 | AB34: =1/(1+((1+Assumptions!$B$6)^(1/12)-1))^A34 | AC34: =AC33+Z34*AB34
A35: 33 | B35: =(1+Assumptions!$B$4)^INT((A35-1)/12) | C35: =MIN(0.95,0.991818*Assumptions!$B$114) | D35: =C35*Assumptions!$B$125 | E35: =Assumptions!$B$112*Assumptions!$B$113*B35 | F35: =D35*E35*Assumptions!$B$16 | G35: =MAX(Assumptions!$B$117*F35,Assumptions!$B$111*Assumptions!$B$32*B35) | H35: =Assumptions!$B$115*Assumptions!$B$116*B35 | I35: =(Assumptions!$B$124+Assumptions!$B$36)*B35 | J35: =MAX(Assumptions!$B$123*B35*D35*Assumptions!$B$16,Assumptions!$B$39*B35) | K35: =Assumptions!$B$40*B35 | L35: =Assumptions!$B$41*B35 | M35: =Assumptions!$B$42 | N35: =F35*Assumptions!$B$44*Assumptions!$B$45+Assumptions!$B$46 | O35: =IF(A35<=12,MAX(Assumptions!$B$47*F35,Assumptions!$B$48*B35),MAX(Assumptions!$B$49*F35,Assumptions!$B$50*B35)) | P35: =(Assumptions!$B$51+IF(Assumptions!$B$118=1,Assumptions!$B$52,0))*B35 | Q35: =MAX(Assumptions!$B$53*F35,Assumptions!$B$54*B35) | R35: =IF(AND(Assumptions!$B$120>0,A35>=2),MAX(Assumptions!$B$120*F35,Assumptions!$B$121),0) | S35: =J35+K35+L35+M35+N35+O35+P35+R35+Q35*Assumptions!$B$55+IF(Assumptions!$B$118=1,G35,0)+IF(Assumptions!$B$119=1,H35,0) | T35: =MAX(Assumptions!$B$58*F35-Assumptions!$B$59*S35,Assumptions!$B$60*F35) | U35: =Assumptions!$B$56+IF(A35>=13,Assumptions!$B$57/12,0) | V35: =SUM(G35:R35)+T35+U35 | W35: =F35-V35 | X35: =(CAPEX!$B$32+Assumptions!$B$122)/Assumptions!$B$68 | Y35: =W35-X35 | Z35: =W35 | AA35: =AA34+Z35 | AB35: =1/(1+((1+Assumptions!$B$6)^(1/12)-1))^A35 | AC35: =AC34+Z35*AB35
A36: 34 | B36: =(1+Assumptions!$B$4)^INT((A36-1)/12) | C36: =MIN(0.95,0.994545*Assumptions!$B$114) | D36: =C36*Assumptions!$B$125 | E36: =Assumptions!$B$112*Assumptions!$B$113*B36 | F36: =D36*E36*Assumptions!$B$16 | G36: =MAX(Assumptions!$B$117*F36,Assumptions!$B$111*Assumptions!$B$32*B36) | H36: =Assumptions!$B$115*Assumptions!$B$116*B36 | I36: =(Assumptions!$B$124+Assumptions!$B$36)*B36 | J36: =MAX(Assumptions!$B$123*B36*D36*Assumptions!$B$16,Assumptions!$B$39*B36) | K36: =Assumptions!$B$40*B36 | L36: =Assumptions!$B$41*B36 | M36: =Assumptions!$B$42 | N36: =F36*Assumptions!$B$44*Assumptions!$B$45+Assumptions!$B$46 | O36: =IF(A36<=12,MAX(Assumptions!$B$47*F36,Assumptions!$B$48*B36),MAX(Assumptions!$B$49*F36,Assumptions!$B$50*B36)) | P36: =(Assumptions!$B$51+IF(Assumptions!$B$118=1,Assumptions!$B$52,0))*B36 | Q36: =MAX(Assumptions!$B$53*F36,Assumptions!$B$54*B36) | R36: =IF(AND(Assumptions!$B$120>0,A36>=2),MAX(Assumptions!$B$120*F36,Assumptions!$B$121),0) | S36: =J36+K36+L36+M36+N36+O36+P36+R36+Q36*Assumptions!$B$55+IF(Assumptions!$B$118=1,G36,0)+IF(Assumptions!$B$119=1,H36,0) | T36: =MAX(Assumptions!$B$58*F36-Assumptions!$B$59*S36,Assumptions!$B$60*F36) | U36: =Assumptions!$B$56+IF(A36>=13,Assumptions!$B$57/12,0) | V36: =SUM(G36:R36)+T36+U36 | W36: =F36-V36 | X36: =(CAPEX!$B$32+Assumptions!$B$122)/Assumptions!$B$68 | Y36: =W36-X36 | Z36: =W36 | AA36: =AA35+Z36 | AB36: =1/(1+((1+Assumptions!$B$6)^(1/12)-1))^A36 | AC36: =AC35+Z36*AB36
A37: 35 | B37: =(1+Assumptions!$B$4)^INT((A37-1)/12) | C37: =MIN(0.95,0.997273*Assumptions!$B$114) | D37: =C37*Assumptions!$B$125 | E37: =Assumptions!$B$112*Assumptions!$B$113*B37 | F37: =D37*E37*Assumptions!$B$16 | G37: =MAX(Assumptions!$B$117*F37,Assumptions!$B$111*Assumptions!$B$32*B37) | H37: =Assumptions!$B$115*Assumptions!$B$116*B37 | I37: =(Assumptions!$B$124+Assumptions!$B$36)*B37 | J37: =MAX(Assumptions!$B$123*B37*D37*Assumptions!$B$16,Assumptions!$B$39*B37) | K37: =Assumptions!$B$40*B37 | L37: =Assumptions!$B$41*B37 | M37: =Assumptions!$B$42 | N37: =F37*Assumptions!$B$44*Assumptions!$B$45+Assumptions!$B$46 | O37: =IF(A37<=12,MAX(Assumptions!$B$47*F37,Assumptions!$B$48*B37),MAX(Assumptions!$B$49*F37,Assumptions!$B$50*B37)) | P37: =(Assumptions!$B$51+IF(Assumptions!$B$118=1,Assumptions!$B$52,0))*B37 | Q37: =MAX(Assumptions!$B$53*F37,Assumptions!$B$54*B37) | R37: =IF(AND(Assumptions!$B$120>0,A37>=2),MAX(Assumptions!$B$120*F37,Assumptions!$B$121),0) | S37: =J37+K37+L37+M37+N37+O37+P37+R37+Q37*Assumptions!$B$55+IF(Assumptions!$B$118=1,G37,0)+IF(Assumptions!$B$119=1,H37,0) | T37: =MAX(Assumptions!$B$58*F37-Assumptions!$B$59*S37,Assumptions!$B$60*F37) | U37: =Assumptions!$B$56+IF(A37>=13,Assumptions!$B$57/12,0) | V37: =SUM(G37:R37)+T37+U37 | W37: =F37-V37 | X37: =(CAPEX!$B$32+Assumptions!$B$122)/Assumptions!$B$68 | Y37: =W37-X37 | Z37: =W37 | AA37: =AA36+Z37 | AB37: =1/(1+((1+Assumptions!$B$6)^(1/12)-1))^A37 | AC37: =AC36+Z37*AB37
A38: 36 | B38: =(1+Assumptions!$B$4)^INT((A38-1)/12) | C38: =MIN(0.95,1.0*Assumptions!$B$114) | D38: =C38*Assumptions!$B$125 | E38: =Assumptions!$B$112*Assumptions!$B$113*B38 | F38: =D38*E38*Assumptions!$B$16 | G38: =MAX(Assumptions!$B$117*F38,Assumptions!$B$111*Assumptions!$B$32*B38) | H38: =Assumptions!$B$115*Assumptions!$B$116*B38 | I38: =(Assumptions!$B$124+Assumptions!$B$36)*B38 | J38: =MAX(Assumptions!$B$123*B38*D38*Assumptions!$B$16,Assumptions!$B$39*B38) | K38: =Assumptions!$B$40*B38 | L38: =Assumptions!$B$41*B38 | M38: =Assumptions!$B$42 | N38: =F38*Assumptions!$B$44*Assumptions!$B$45+Assumptions!$B$46 | O38: =IF(A38<=12,MAX(Assumptions!$B$47*F38,Assumptions!$B$48*B38),MAX(Assumptions!$B$49*F38,Assumptions!$B$50*B38)) | P38: =(Assumptions!$B$51+IF(Assumptions!$B$118=1,Assumptions!$B$52,0))*B38 | Q38: =MAX(Assumptions!$B$53*F38,Assumptions!$B$54*B38) | R38: =IF(AND(Assumptions!$B$120>0,A38>=2),MAX(Assumptions!$B$120*F38,Assumptions!$B$121),0) | S38: =J38+K38+L38+M38+N38+O38+P38+R38+Q38*Assumptions!$B$55+IF(Assumptions!$B$118=1,G38,0)+IF(Assumptions!$B$119=1,H38,0) | T38: =MAX(Assumptions!$B$58*F38-Assumptions!$B$59*S38,Assumptions!$B$60*F38) | U38: =Assumptions!$B$56+IF(A38>=13,Assumptions!$B$57/12,0) | V38: =SUM(G38:R38)+T38+U38 | W38: =F38-V38 | X38: =(CAPEX!$B$32+Assumptions!$B$122)/Assumptions!$B$68 | Y38: =W38-X38 | Z38: =W38 | AA38: =AA37+Z38 | AB38: =1/(1+((1+Assumptions!$B$6)^(1/12)-1))^A38 | AC38: =AC37+Z38*AB38
A39: Год 1 | F39: =SUM(F3:F14) | G39: =SUM(G3:G14) | H39: =SUM(H3:H14) | I39: =SUM(I3:I14) | J39: =SUM(J3:J14) | K39: =SUM(K3:K14) | L39: =SUM(L3:L14) | M39: =SUM(M3:M14) | ... Y39: =SUM(Y3:Y14)
A40: Год 2 | F40: =SUM(F15:F26) | G40: =SUM(G15:G26) | H40: =SUM(H15:H26) | I40: =SUM(I15:I26) | J40: =SUM(J15:J26) | K40: =SUM(K15:K26) | L40: =SUM(L15:L26) | M40: =SUM(M15:M26) | ... Y40: =SUM(Y15:Y26)
A41: Год 3 | F41: =SUM(F27:F38) | G41: =SUM(G27:G38) | H41: =SUM(H27:H38) | I41: =SUM(I27:I38) | J41: =SUM(J27:J38) | K41: =SUM(K27:K38) | L41: =SUM(L27:L38) | M41: =SUM(M27:M38) | ... Y41: =SUM(Y27:Y38)
A43: NPV @discount_rate, 36 мес. | F43: =Z2+SUMPRODUCT(Z3:Z38,AB3:AB38)
A44: IRR годовая | F44: =(1+IRR(Z2:Z38))^12-1
A45: Окупаемость простая, мес. | F45: =IFERROR(INDEX(A3:A38,MATCH(TRUE,INDEX(AA3:AA38>=0,0),0)),"нет за 36 мес.")
A46: Окупаемость дисконтированная, мес. | F46: =IFERROR(INDEX(A3:A38,MATCH(TRUE,INDEX(AC3:AC38>=0,0),0)),"нет за 36 мес.")
A47: Проверка: Σ(выручка − расходы − EBITDA) = 0 | F47: =SUM(F3:F38)-SUM(V3:V38)-SUM(W3:W38)
A48: Проверка: мин(налог − 4,5% выручки) ≥ 0 | F48: =MIN(INDEX(T3:T38-0.045*F3:F38,0))

Sheet Scenarios
A1: Показатель | B1: Пессимистичный | C1: Базовый | D1: Оптимистичный
A2: Параметры: цена ×, зрелая загрузка, аренда AMD/м², схема мастеров | B2: 0,9 / 30% / 8 000 / сотрудники (a) | C2: 1,0 / 40% / 6 500 / ИП (c) | D2: 1,0 / 45% / 5 800 / ИП (c)
A3: Выручка, год 1 | B3: 15988633 | C3: 23686864 | D3: 26647722
A4: Выплаты мастерам, год 1 | B4: 9773561 | C4: 12547186 | D4: 13816379
A5: Налог с оборота, год 1 | B5: 1345231 | C5: 1366960 | D5: 1560284
A6: EBITDA, год 1 | B6: -4564355 | C6: 438885 | D6: 1915019
A7: Чистая прибыль, год 1 | B7: -6079845 | C7: -1076605 | D7: 399529
A8: Услуг/день, среднее за год 1 | B8: 20.8 | C8: 27.7 | D8: 31.1
A9: Выручка, год 2 | B9: 23414842 | C9: 34688655 | D9: 39024737
A10: Выплаты мастерам, год 2 | B10: 11707421 | C10: 17344327 | D10: 19512368
A11: Налог с оборота, год 2 | B11: 2093224 | C11: 2136039 | D11: 2417057
A12: EBITDA, год 2 | B12: -133616 | C12: 5179174 | D12: 6910550
A13: Чистая прибыль, год 2 | B13: -1649106 | C13: 3663684 | D13: 5395060
A14: Услуг/день, среднее за год 2 | B14: 29.1 | C14: 38.9 | D14: 43.7
... A23: Потребность в финансировании | B23: 14842176 | C23: 11864370 | D23: 11528237
A24: Окупаемость простая, мес. | B24: нет за 36 | C24: 31 | D24: 25
A25: Окупаемость дисконтированная, мес. | B25: нет за 36 | C25: нет за 36 | D25: 29
A26: NPV 36 мес. @18% | B26: -13255155 | C26: -545180 | D26: 3481614
A27: NPV 36 мес. @18% с TV 3×EBITDA Y3 | B27: -12388299 | C27: 11065459 | D27: 18603450
A28: IRR годовая | B28: -74.4% | C28: 14.5% | D28: 40.6%

Sheet Sensitivity
A1: Фактор | B1: −20% | C1: −10% | D1: база | E1: +10% | F1: +20% | G1: Показатель
A2: Цена | B2: -518145 | C2: 3509571 | D2: 7430473 | E2: 11278307 | F2: 15051330 | G2: Чистая прибыль 36 мес.
A3: Цена | B3: >36 | C3: >36 | D3: 31 | E3: 26 | F3: 23 | G3: Окупаемость, мес.
A4: Цена | B4: -6697458 | C4: -3571801 | D4: -545180 | E4: 2414882 | F4: 5303956 | G4: NPV @18%
A5: Загрузка | B5: 222228 | C5: 3880668 | D5: 7430473 | E5: 10907210 | F5: 14309680 | G5: Чистая прибыль 36 мес.
A6: Загрузка | B6: >36 | C6: >36 | D6: 31 | E6: 26 | F6: 23 | G6: Окупаемость, мес.
A7: Загрузка | B7: -6135756 | C7: -3290043 | D7: -545180 | E7: 2133124 | F7: 4740970 | G7: NPV @18%
A8: Аренда | B8: 8895711 | C8: 8163092 | D8: 7430473 | E8: 6697855 | F8: 5965236 | G8: Чистая прибыль 36 мес.
A9: Аренда | B9: 29 | C9: 30 | D9: 31 | E9: 32 | F9: 34 | G9: Окупаемость, мес.
A10: Аренда | B10: 723205 | C10: 89012 | D10: -545180 | E10: -1179373 | F10: -1813566 | G10: NPV @18%
A11: Доля ФОТ | B11: 16111305 | C11: 11810751 | D11: 7430473 | E11: 3015708 | F11: -1449988 | G11: Чистая прибыль 36 мес.
A12: Доля ФОТ | B12: 22 | C12: 26 | D12: 31 | E12: >36 | F12: >36 | G12: Окупаемость, мес.
A13: Доля ФОТ | B13: 5948455 | C13: 2739136 | D13: -545180 | E13: -3862133 | F13: -7227952 | G13: NPV @18%
A15: Переключатели | B15: Налог м36 | C15: Чистая прибыль м36 | D15: Чистая прибыль 36 мес. | E15: Окупаемость | F15: NPV @18%
A16: База (ИП-мастера, аренда у физлица, 40 м², маркетинг 5%→3%) | B16: 203829 | C16: 420356 | D16: 7430473 | E16: 31 | F16: -545180
A17: Мастера — сотрудники (ФОТ не вычитается), схема (a) | B17: 303661 | C17: 336841 | D17: 5025109 | E17: 35 | F17: -2363351
A18: Мастера — сотрудники с gross-up до 50% на руки, схема (b) | B18: 303661 | C18: -293824 | D18: -13295230 | E18: >36 | F18: -16282975
A19: Арендодатель выдаёт документы (аренда вычитается) | B19: 191101 | C19: 433084 | D19: 7844241 | E19: 30 | F19: -227917
A20: Аренда 9 500/м² (единственное малое объявление в спальном районе) | B20: 203829 | C20: 322450 | D20: 4049156 | E20: >36 | F20: -3472225
A21: Аренда 5 800/м² (медиана n=3) | B21: 203829 | C21: 443201 | D21: 8219447 | E21: 30 | F21: 137796
A22: Драм −10% → аренда +10% | B22: 203829 | C22: 399143 | D22: 6697855 | E22: 32 | F22: -1115998
A23: Маркетинг 5% все 3 года | B23: 199875 | C23: 358408 | D23: 6046101 | E23: 33 | F23: -1531554
A24: Доля ФОТ 55% | B24: 193944 | C24: 265486 | D24: 3015708 | E24: >36 | F24: -3862133
A25: Администратор-хост 150 000 в мес. 1–6 | B25: 203829 | C25: 420356 | D25: 6530473 | E25: 33 | F25: -1403003
A26: Владелец-оператор (без управляющего) | B26: 203829 | C26: 550898 | D26: 11938896 | E26: 25 | F26: 2967545
A27: Площадь 40 м² как в v1 (аренда 260 000, fit-out 4,0 млн) | B27: 203829 | C27: 330479 | D27: 4298411 | E27: >36 | F27: -3809157
A28: Прайс A+: муж. 2 800, машинка/детская 2 200, жен. 2 800/3 800 (чек +9,5%, −7% к медиане эконом) | B28: 224899 | C28: 538414 | D28: 11090145 | E28: 26 | F28: 2270205

Sheet Schemes
A1: Схема оплаты мастеров (мес. 36 базы) | B1: Брутто на мастера, AMD | C1: На руки мастеру, AMD | D1: На руки, % выручки точки | E1: Стоимость для салона (4 мастера) | F1: Вычет 6% для салона
A2: (a) Трудовой договор, 50% выручки gross | B2: 411888 | C2: 303116 | D2: 36.8 | E2: 1647553 | F2: нет
A3: (b) Трудовой договор, 50% выручки НА РУКИ (gross-up) | B3: 569555 | C3: 411888 | D3: 50 | E3: 2278219 | F3: нет
A4: (c) Мастер-ИП (налог с оборота), 50% выручки — базовая | B4: 411888 | C4: 350135 | D4: 42.5 | E4: 1647553 | F4: да

Sheet Franchise
A1: Паушальный | B1: Роялти | C1: Окупаемость, мес. | D1: Маржа м36 | E1: NPV 36 мес. @18% | F1: NPV 60 мес. @18% | G1: IRR 60 мес. | H1: CAPEX субфранчайзи
A2: 800000 | B2: 0.025 | C2: 37 | D2: 0.1 | E2: -3106158 | F2: 3086771 | G2: 0.2909 | H2: 9784200
A3: 800000 | B3: 0.03 | C3: 38 | D3: 0.0953 | E3: -3429087 | F3: 2560420 | G3: 0.2725 | H3: 9784200
A4: 800000 | B4: 0.04 | C4: 40 | D4: 0.0859 | E4: -4098741 | F4: 1483919 | G4: 0.2341 | H4: 9784200
A5: 1000000 | B5: 0.025 | C5: 37 | D5: 0.099 | E5: -3306158 | F5: 2886771 | G5: 0.2823 | H5: 9984200
A6: 1000000 | B6: 0.03 | C6: 38 | D6: 0.0943 | E6: -3629087 | F6: 2360420 | G6: 0.2641 | H6: 9984200
A7: 1000000 | B7: 0.04 | C7: 40 | D7: 0.0849 | E7: -4298741 | F7: 1283919 | G7: 0.2262 | H7: 9984200
A8: 1200000 | B8: 0.025 | C8: 38 | D8: 0.098 | E8: -3506158 | F8: 2686771 | G8: 0.2739 | H8: 10184200
A9: 1200000 | B9: 0.03 | C9: 39 | D9: 0.0933 | E9: -3829087 | F9: 2160420 | G9: 0.2559 | H9: 10184200
A10: 1200000 | B10: 0.04 | C10: 41 | D10: 0.0839 | E10: -4498741 | F10: 1083919 | G10: 0.2185 | H10: 10184200
A11: 1500000 | B11: 0.025 | C11: 38 | D11: 0.0965 | E11: -3806158 | F11: 2386771 | G11: 0.2618 | H11: 10484200
A12: 1500000 | B12: 0.03 | C12: 39 | D12: 0.0918 | E12: -4129087 | F12: 1860420 | G12: 0.2441 | H12: 10484200
A13: 1500000 | B13: 0.04 | C13: 41 | D13: 0.0824 | E13: -4798741 | F13: 783919 | G13: 0.2073 | H13: 10484200

Sheet Network
A1: Мес. | B1: Собств. | C1: Франч. | D1: Выручка собств. | E1: Выручка франч. | F1: EBITDA собств. | G1: Роялти | H1: Фонд (транзит) | I1: Маржа поставок | J1: Паушальные | K1: Расходы УК | L1: Налог УК | M1: Результат холдинга | N1: Результат без паушальных | O1: CAPEX | P1: CF | Q1: Накопл. CF | R1: Накопл. CF без паушальных
A2: 1 | B2: 1 | C2: 0 | D2: 848123 | E2: 0 | F2: -694090 | G2: 0 | H2: 0 | I2: 0 | J2: 0 | K2: 0 | L2: 0 | M2: -694090 | N2: -694090 | O2: 8984200 | P2: -9678290 | Q2: -9678290 | R2: -9678290
A3: 2 | B3: 1 | C3: 0 | D3: 1120734 | E3: 0 | F3: -448841 | G3: 0 | H3: 0 | I3: 0 | J3: 0 | K3: 0 | L3: 0 | M3: -448841 | N3: -448841 | O3: 0 | P3: -448841 | Q3: -10127131 | R3: -10127131
A4: 3 | B4: 1 | C4: 0 | D4: 1423635 | E4: 0 | F4: -189014 | G4: 0 | H4: 0 | I4: 0 | J4: 0 | K4: 0 | L4: 0 | M4: -189014 | N4: -189014 | O4: 0 | P4: -189014 | Q4: -10316145 | R4: -10316145
A5: 4 | B5: 1 | C5: 0 | D5: 1696246 | E5: 0 | F5: -6107 | G5: 0 | H5: 0 | I5: 0 | J5: 0 | K5: 0 | L5: 0 | M5: -6107 | N5: -6107 | O5: 0 | P5: -6107 | Q5: -10322252 | R5: -10322252
A6: 5 | B6: 1 | C6: 0 | D6: 1908277 | E6: 0 | F6: 71683 | G6: 0 | H6: 0 | I6: 0 | J6: 0 | K6: 0 | L6: 0 | M6: 71683 | N6: 71683 | O6: 0 | P6: 71683 | Q6: -10250569 | R6: -10250569
A7: 6 | B7: 1 | C7: 0 | D7: 2120308 | E7: 0 | F7: 149472 | G7: 0 | H7: 0 | I7: 0 | J7: 0 | K7: 0 | L7: 0 | M7: 149472 | N7: 149472 | O7: 0 | P7: 149472 | Q7: -10101097 | R7: -10101097
A8: 7 | B8: 1 | C8: 0 | D8: 2241468 | E8: 0 | F8: 193923 | G8: 0 | H8: 0 | I8: 0 | J8: 0 | K8: 650000 | L8: 0 | M8: -456077 | N8: -456077 | O8: 0 | P8: -456077 | Q8: -10557174 | R8: -10557174
A9: 8 | B9: 2 | C9: 0 | D9: 3180461 | E9: 0 | F9: -466828 | G9: 0 | H9: 0 | I9: 0 | J9: 0 | K9: 650000 | L9: 0 | M9: -1116828 | N9: -1116828 | O9: 8984200 | P9: -10101028 | Q9: -20658202 | R9: -20658202
A10: 9 | B10: 2 | C10: 0 | D10: 3513652 | E10: 0 | F10: -199354 | G10: 0 | H10: 0 | I10: 0 | J10: 0 | K10: 650000 | L10: 0 | M10: -849354 | N10: -849354 | O10: 0 | P10: -849354 | Q10: -21507556 | R10: -21507556
A11: 10 | B11: 2 | C11: 0 | D11: 3877134 | E11: 0 | F11: 80185 | G11: 0 | H11: 0 | I11: 0 | J11: 0 | K11: 650000 | L11: 0 | M11: -569815 | N11: -569815 | O11: 0 | P11: -569815 | Q11: -22077371 | R11: -22077371
A12: 11 | B12: 2 | C12: 0 | D12: 4240615 | E12: 0 | F12: 292159 | G12: 0 | H12: 0 | I12: 0 | J12: 0 | K12: 650000 | L12: 0 | M12: -357841 | N12: -357841 | O12: 0 | P12: -357841 | Q12: -22435211 | R12: -22435211
A13: 12 | B13: 2 | C13: 0 | D13: 4513226 | E13: 0 | F13: 389327 | G13: 0 | H13: 0 | I13: 0 | J13: 0 | K13: 650000 | L13: 0 | M13: -260673 | N13: -260673 | O13: 3000000 | P13: -3260673 | Q13: -25695884 | R13: -25695884
... A37: 36 | B37: 3 | C37: 7 | D37: 8858480 | E37: 15409404 | F37: 1420909 | G37: 436838 | H37: 154094 | I37: 124852 | J37: 1000000 | K37: 1300000 | L37: 159290 | M37: 1523309 | N37: 623309 | O37: 0 | P37: 1523309 | Q37: -30143937 | R37: -36443937
